{"edges":[{"label":"","source":"4","target":"4","id":"6","attributes":{},"color":"rgb(215, 158, 175)","size":1.0},{"label":"","source":"5","target":"5","id":"8","attributes":{},"color":"rgb(114, 171, 75)","size":1.0},{"label":"","source":"7","target":"7","id":"10","attributes":{},"color":"rgb(162, 127, 229)","size":1.0},{"label":"","source":"8","target":"8","id":"12","attributes":{},"color":"rgb(162, 127, 229)","size":1.0},{"label":"","source":"9","target":"9","id":"14","attributes":{},"color":"rgb(152, 164, 166)","size":1.0},{"label":"","source":"10","target":"10","id":"16","attributes":{},"color":"rgb(181, 163, 247)","size":1.0},{"label":"","source":"13","target":"13","id":"18","attributes":{},"color":"rgb(146, 246, 89)","size":1.0},{"label":"","source":"14","target":"14","id":"20","attributes":{},"color":"rgb(114, 171, 75)","size":1.0},{"label":"","source":"18","target":"18","id":"22","attributes":{},"color":"rgb(215, 158, 175)","size":1.0},{"label":"","source":"22","target":"22","id":"24","attributes":{},"color":"rgb(84, 14, 195)","size":1.0},{"label":"","source":"23","target":"23","id":"26","attributes":{},"color":"rgb(162, 127, 229)","size":1.0},{"label":"","source":"25","target":"25","id":"28","attributes":{},"color":"rgb(63, 81, 159)","size":1.0},{"label":"","source":"26","target":"26","id":"30","attributes":{},"color":"rgb(114, 171, 75)","size":1.0},{"label":"","source":"26","target":"31","id":"32","attributes":{},"color":"rgb(114, 171, 75)","size":1.0},{"label":"","source":"28","target":"28","id":"34","attributes":{},"color":"rgb(114, 171, 75)","size":1.0},{"label":"","source":"29","target":"29","id":"36","attributes":{},"color":"rgb(114, 171, 75)","size":1.0},{"label":"","source":"30","target":"8","id":"38","attributes":{},"color":"rgb(162, 127, 229)","size":1.0},{"label":"","source":"30","target":"30","id":"40","attributes":{},"color":"rgb(114, 171, 75)","size":1.0},{"label":"","source":"31","target":"30","id":"42","attributes":{},"color":"rgb(114, 171, 75)","size":1.0},{"label":"","source":"31","target":"31","id":"44","attributes":{},"color":"rgb(114, 171, 75)","size":1.0},{"label":"","source":"32","target":"29","id":"46","attributes":{},"color":"rgb(114, 171, 75)","size":1.0},{"label":"","source":"32","target":"32","id":"48","attributes":{},"color":"rgb(114, 171, 75)","size":1.0},{"label":"","source":"34","target":"34","id":"50","attributes":{},"color":"rgb(226, 157, 97)","size":1.0},{"label":"","source":"35","target":"35","id":"52","attributes":{},"color":"rgb(162, 127, 229)","size":1.0},{"label":"","source":"36","target":"26","id":"54","attributes":{},"color":"rgb(114, 171, 75)","size":1.0},{"label":"","source":"36","target":"36","id":"56","attributes":{},"color":"rgb(114, 171, 75)","size":1.0},{"label":"","source":"37","target":"37","id":"58","attributes":{},"color":"rgb(146, 246, 89)","size":1.0},{"label":"","source":"38","target":"0","id":"60","attributes":{},"color":"rgb(162, 236, 190)","size":1.0},{"label":"","source":"39","target":"1","id":"62","attributes":{},"color":"rgb(162, 236, 190)","size":1.0},{"label":"","source":"40","target":"1","id":"64","attributes":{},"color":"rgb(162, 236, 190)","size":1.0},{"label":"","source":"40","target":"15","id":"66","attributes":{},"color":"rgb(162, 236, 190)","size":1.0},{"label":"","source":"41","target":"2","id":"68","attributes":{},"color":"rgb(162, 236, 190)","size":1.0},{"label":"","source":"42","target":"3","id":"70","attributes":{},"color":"rgb(162, 236, 190)","size":1.0},{"label":"","source":"43","target":"4","id":"72","attributes":{},"color":"rgb(215, 158, 175)","size":1.0},{"label":"","source":"43","target":"9","id":"74","attributes":{},"color":"rgb(152, 164, 166)","size":1.0},{"label":"","source":"43","target":"14","id":"76","attributes":{},"color":"rgb(114, 171, 75)","size":1.0},{"label":"","source":"43","target":"18","id":"78","attributes":{},"color":"rgb(215, 158, 175)","size":1.0},{"label":"","source":"43","target":"23","id":"80","attributes":{},"color":"rgb(162, 127, 229)","size":1.0},{"label":"","source":"43","target":"29","id":"82","attributes":{},"color":"rgb(114, 171, 75)","size":1.0},{"label":"","source":"43","target":"32","id":"84","attributes":{},"color":"rgb(114, 171, 75)","size":1.0},{"label":"","source":"43","target":"34","id":"86","attributes":{},"color":"rgb(226, 157, 97)","size":1.0},{"label":"","source":"43","target":"35","id":"88","attributes":{},"color":"rgb(162, 127, 229)","size":1.0},{"label":"","source":"43","target":"37","id":"90","attributes":{},"color":"rgb(146, 246, 89)","size":1.0},{"label":"","source":"44","target":"6","id":"92","attributes":{},"color":"rgb(162, 236, 190)","size":1.0},{"label":"","source":"45","target":"7","id":"94","attributes":{},"color":"rgb(162, 127, 229)","size":1.0},{"label":"","source":"45","target":"13","id":"96","attributes":{},"color":"rgb(146, 246, 89)","size":1.0},{"label":"","source":"45","target":"23","id":"98","attributes":{},"color":"rgb(162, 127, 229)","size":1.0},{"label":"","source":"45","target":"35","id":"100","attributes":{},"color":"rgb(162, 127, 229)","size":1.0},{"label":"","source":"45","target":"37","id":"102","attributes":{},"color":"rgb(146, 246, 89)","size":1.0},{"label":"","source":"47","target":"9","id":"104","attributes":{},"color":"rgb(152, 164, 166)","size":1.0},{"label":"","source":"47","target":"9","id":"106","attributes":{},"color":"rgb(152, 164, 166)","size":1.0},{"label":"","source":"47","target":"25","id":"108","attributes":{},"color":"rgb(63, 81, 159)","size":1.0},{"label":"","source":"47","target":"29","id":"110","attributes":{},"color":"rgb(114, 171, 75)","size":1.0},{"label":"","source":"47","target":"32","id":"112","attributes":{},"color":"rgb(114, 171, 75)","size":1.0},{"label":"","source":"47","target":"34","id":"114","attributes":{},"color":"rgb(226, 157, 97)","size":1.0},{"label":"","source":"47","target":"35","id":"116","attributes":{},"color":"rgb(162, 127, 229)","size":1.0},{"label":"","source":"49","target":"10","id":"118","attributes":{},"color":"rgb(181, 163, 247)","size":1.0},{"label":"","source":"50","target":"11","id":"120","attributes":{},"color":"rgb(162, 236, 190)","size":1.0},{"label":"","source":"51","target":"12","id":"122","attributes":{},"color":"rgb(162, 236, 190)","size":1.0},{"label":"","source":"55","target":"16","id":"124","attributes":{},"color":"rgb(162, 236, 190)","size":1.0},{"label":"","source":"56","target":"17","id":"126","attributes":{},"color":"rgb(162, 236, 190)","size":1.0},{"label":"","source":"58","target":"19","id":"128","attributes":{},"color":"rgb(162, 236, 190)","size":1.0},{"label":"","source":"59","target":"20","id":"130","attributes":{},"color":"rgb(162, 236, 190)","size":1.0},{"label":"","source":"60","target":"21","id":"132","attributes":{},"color":"rgb(162, 236, 190)","size":1.0},{"label":"","source":"61","target":"22","id":"134","attributes":{},"color":"rgb(84, 14, 195)","size":1.0},{"label":"","source":"64","target":"24","id":"136","attributes":{},"color":"rgb(162, 236, 190)","size":1.0},{"label":"","source":"65","target":"25","id":"138","attributes":{},"color":"rgb(63, 81, 159)","size":1.0},{"label":"","source":"66","target":"25","id":"140","attributes":{},"color":"rgb(63, 81, 159)","size":1.0},{"label":"","source":"67","target":"25","id":"142","attributes":{},"color":"rgb(63, 81, 159)","size":1.0},{"label":"","source":"68","target":"25","id":"144","attributes":{},"color":"rgb(63, 81, 159)","size":1.0},{"label":"","source":"70","target":"27","id":"146","attributes":{},"color":"rgb(162, 236, 190)","size":1.0},{"label":"","source":"75","target":"33","id":"148","attributes":{},"color":"rgb(162, 236, 190)","size":1.0}],"nodes":[{"label":"LATAM-388","x":0.0,"y":1.0,"id":"0","attributes":{"Title":"Postmodernism & Latin America","Description":"Spring\n2015\nLatin American Studies\n388\nMount Holyoke College\nFor many the 'discovery' of America opened the modern era. Its closing may also have been foretold in Latin America's confounding of diverse theories of modernization and development in recent times. This seminar will introduce the student to a number of both classic and more recent works on Latin America (in English) that advance along postmodernist lines, ranging from cultural contact and conflict, language, meaning, and power in the sixteenth century, to the invention of national identities in the nineteenth century, to discourses of ethnicity, class, gender, and reason in the twentieth century.\nThis course is open to Juniors and Seniors.; Prereq: 8 credits in Latin American studies or related field.\nPermission is required for interchange registration during the add/drop period only.\n90926,91139\n91139\n \n ","Department Code":"LATAM","Course Site":"<a href= 'https://www.fivecolleges.edu/courses/MHC/2015/SPRING/LATAM/388/01'> Course Site </a>","Requisite":[]},"color":"rgb(162, 236, 190)","size":10.0},{"label":"LATAM-227","x":1.0,"y":1.0,"id":"1","attributes":{"Title":"Intermed. Portuguese for Span.","Description":"Spring\n2015\nLatin American Studies\n227\nMount Holyoke College\nThe goal of this course is to offer students sophisticated linguistic tools that will allow them to interact and communicate in Portuguese in socio-cultural contexts that go beyond their immediate personal experience and daily life. The course is designed for students who have previous experience with Portuguese and are already familiar with the majority of the grammatical structures of the language. Through the use of authentic written texts, videos, and songs, students will broaden and deepen their reading, writing, listening, and speaking abilities in Portuguese.\nPrereq: Spanish 217.\nCourse taught in Portuguese.\nPermission is required for interchange registration during the add/drop period only.\n91653,91650\n91653\n \n ","Department Code":"LATAM","Course Site":"<a href= 'https://www.fivecolleges.edu/courses/MHC/2015/SPRING/LATAM/227/01'> Course Site </a>","Requisite":[]},"color":"rgb(162, 236, 190)","size":10.0},{"label":"LATAM-287RC","x":3.0,"y":1.0,"id":"2","attributes":{"Title":"Re-Imagining the Caribbean","Description":"Fall\n2014\nLatin American Studies\n287RC\nMount Holyoke College\nThe Caribbean has been formed through a complex interaction of the peoples of Africa, Asia, Europe, Latin American and the United States.  In this introductory, interdisciplinary course we will examine the major issues that have shaped modern Caribbean society, including colonialism, revolution, nationalism, self-determination, transition from agricultural to tourism-based economies, migration, and globalization.  Particular attention will be given to Cuba, Haiti, Jamaica, Trinidad, Puerto Rico, and the Dominican Republic, but we will also consider relevant examples from other areas of the region.   In addition to historical documents, we will also consider literature, art, and film.\nPermission is required for interchange registration during the add/drop period only.\n89570\n \n ","Department Code":"LATAM","Course Site":"<a href= 'https://www.fivecolleges.edu/courses/MHC/2014/FALL/LATAM/287RC/01'> Course Site </a>","Requisite":[]},"color":"rgb(162, 236, 190)","size":10.0},{"label":"LATAM-387CM","x":4.0,"y":1.0,"id":"3","attributes":{"Title":"Puerto Rican Studies","Description":"Spring\n2015\nLatin American Studies\n387CM\nMount Holyoke College\nThrough lectures, class discussions, outside speakers, films and site visits, this Community-Based Learning course will engage Puerto Rican history, culture, and immigration with a focus on Puerto Rican communities in Western Massachusetts.  In particular, Students will understand how Puerto Ricans in Holyoke have negotiated their cultural identity and place in the educational system.  In partnership with the Holyoke Public Schools, students will assist with a project based upon the needs of educators to develop materials to forge greater intercultural understanding and enhance learning outcomes for HPS students. Taught mostly in English with some materials and discussion in Spanish.\nPrereq: Spanish 201.\nTaught in both English and Spanish according to level of Spanish proficiency of students enrolled.  Intermediate Spanish (201) is required for those who are not Spanish majors or minors.\nPermission is required for interchange registration during the add/drop period only.\n91654,91652,91612\n91654\n \n ","Department Code":"LATAM","Course Site":"<a href= 'https://www.fivecolleges.edu/courses/MHC/2015/SPRING/LATAM/387CM/01'> Course Site </a>","Requisite":[]},"color":"rgb(162, 236, 190)","size":10.0},{"label":"GEOG-312LT","x":9.5,"y":1.0,"id":"4","attributes":{"Title":"Envir/Developmet in Latin Am.","Description":"Spring\n2015\nGeography\n312LT\nMount Holyoke College\nThis course examines the spatially uneven, changing, and contested relationships between environment and development in Central and South America. We will focus on theories of development and of the causes and consequences of environmental degradation, reading these theories through the recent history of Latin America. Major topics include (post)colonialism, biodiversity conservation, resource extraction, gender relations, poverty reduction, peasantries and agriculture, and vulnerability to global change.\nThis course is open to Juniors and Seniors.; Prereq: One course from the department and one course in related social sciences at the 200-level.\nPermission is required for interchange registration during the add/drop period only.\n91646\n \n ","Department Code":"GEOG","Course Site":"<a href= 'https://www.fivecolleges.edu/courses/MHC/2015/SPRING/GEOG/312LT/01'> Course Site </a>","Requisite":[]},"color":"rgb(215, 158, 175)","size":10.0},{"label":"LATIN-350","x":19.0,"y":0.0,"id":"5","attributes":{"Title":"Junior/Senior Tutorial","Description":"Fall\n2015\nLatin\n350\nMount Holyoke College\nThis course is open to Juniors and Seniors.; Prereq: 8 credits of advanced work in Latin.\n2.00-4.00 credits. Meets Humanities or Language requirement if taken for four credits.\nPermission is required for interchange registration during all registration periods.\n93695\n \n ","Department Code":"LATIN","Course Site":"<a href= 'https://www.fivecolleges.edu/courses/MHC/2015/FALL/LATIN/350/01'> Course Site </a>","Requisite":[]},"color":"rgb(114, 171, 75)","size":10.0},{"label":"LATAM-180","x":20.0,"y":1.0,"id":"6","attributes":{"Title":"Intro to Latin American Cultrs","Description":"Spring\n2016\nLatin American Studies\n180\nMount Holyoke College\nExamines the confrontation, assimilation, and transformation of Amerindian, African, and European cultures in Latin America from the sixteenth century to the present. Focuses on the processes in which distinctive self-images emerged in the region and how these images have been challenged and changed over time. Uses films, literature, and folk traditions to complement scholarly analysis of the emergence of a New World mentality.\nPermission is required for interchange registration during the add/drop period only.\n95013,94780\n95013\n \n ","Department Code":"LATAM","Course Site":"<a href= 'https://www.fivecolleges.edu/courses/MHC/2016/SPRING/LATAM/180/01'> Course Site </a>","Requisite":[]},"color":"rgb(162, 236, 190)","size":10.0},{"label":"SPAN-240CN","x":16.0,"y":1.0,"id":"7","attributes":{"Title":"Spanish and Latin Amer Cinema","Description":"Fall\n2015\nSpanish\n240CN\nMount Holyoke College\nThis semester's course offers a broad introduction to the history, politics and aesthetics of Latin American and Spanish cinema. The course also introduces students to the basic terminology and methodologies of film studies.\nPrereq: Spanish 212.\nPermission is required for interchange registration during the add/drop period only.\n93409,93400\n93409\n \n ","Department Code":"SPAN","Course Site":"<a href= 'https://www.fivecolleges.edu/courses/MHC/2015/FALL/SPAN/240CN/01'> Course Site </a>","Requisite":[]},"color":"rgb(162, 127, 229)","size":10.0},{"label":"SPAN-260BL","x":21.0,"y":4.0,"id":"8","attributes":{"Title":"Being Bilingual","Description":"Spring\n2016\nSpanish\n260BL\nMount Holyoke College\nThis course will introduce students to key issues and concepts in the study of bilingualism with a focus on communities in which Spanish interacts with other languages in Latin America, Spain, and the United States. One of the main goals of the course is to create awareness about the multidimensional nature of bilingualism as an individual, socio-political, cultural, and a psycholinguistic phenomenon. Topics will include degrees of bilingualism and the notion of bilingual continua, language acquisition and language processing, relations between language and identity, the linguistic effects of other languages in different Spanish varieties, language maintenance and language loss, language policies and bilingual education.\nPrereq: Spanish 209.\nPermission is required for interchange registration during the add/drop period only.\n95564\n \n ","Department Code":"SPAN","Course Site":"<a href= 'https://www.fivecolleges.edu/courses/MHC/2016/SPRING/SPAN/260BL/01'> Course Site </a>","Requisite":[]},"color":"rgb(162, 127, 229)","size":10.0},{"label":"ROMLG-375HS","x":6.5,"y":1.0,"id":"9","attributes":{"Title":"History of Romance Languages","Description":"Spring\n2015\nRomance Lang. & Literature\n375HS\nMount Holyoke College\nThis course examines the structural evolution of Romance languages from Vulgar Latin to contemporary forms. A chronological account will be organized around themes of persistence (inheritance from Latin) and innovation (structural change). We will begin by exploring different theories about linguistic change. Then, using concrete examples, we will analyze the main stages of development of Romance languages by focusing on different features at all linguistic levels and relating them to historical and sociological factors.\nPrereq: for language majors: two courses in culture and literature at the 200 or 300-level in a romance language.\nStudents wishing to obtain 300-level credit in French, Italian, or Spanish must read texts and write papers in the Romance language for which they wish to receive credit.\nPermission is required for interchange registration during the add/drop period only.\n91162,91252,90879,90766\n91162\n \n ","Department Code":"ROMLG","Course Site":"<a href= 'https://www.fivecolleges.edu/courses/MHC/2015/SPRING/ROMLG/375HS/01'> Course Site </a>","Requisite":[]},"color":"rgb(152, 164, 166)","size":10.0},{"label":"STAT-240","x":22.0,"y":1.0,"id":"10","attributes":{"Title":"Elem Data Analysis/Exper Desgn","Description":"Fall\n2015\nStatistics\n240\nMount Holyoke College\nA fundamental fact of science is that repeated measurements exhibit variability. The course presents ways to design experiments that will reveal systematic patterns while 'controlling' the effects of variability and methods for the statistical analysis of data from well-designed experiments. Topics include completely randomized, randomized complete block, Latin Square and factorial designs, and their analysis of variance. The course emphasizes applications, with examples drawn principally from biology, psychology, and medicine.\nPrereq: Any 100 level Mathematics or  Statistics course or permission  of instructor.\nPermission is required for interchange registration during the add/drop period only.\n93334\n \n ","Department Code":"STAT","Course Site":"<a href= 'https://www.fivecolleges.edu/courses/MHC/2015/FALL/STAT/240/01'> Course Site </a>","Requisite":[]},"color":"rgb(181, 163, 247)","size":10.0},{"label":"LATAM-277","x":23.0,"y":1.0,"id":"11","attributes":{"Title":"Caribbean Women Writers","Description":"Fall\n2015\nLatin American Studies\n277\nMount Holyoke College\nComparative examination of contemporary women's writing in the Caribbean. Emphasis will be on their engagement with issues of history, cultural articulation, race, class, gender, and nationality, including exploration of their formal procedures, individual moods, regional particularity, and general impact as writers. Rosario Ferr\u00e9, Ana Lydia Vega, Julia Alvarez, Edna Brodber, Maryse Cond\u00e9, Simone Schwarz-Bart, Jean Rhys, Beryl Gilroy, and Rosa Guy are among those whose works we will review.\nPermission is required for interchange registration during the add/drop period only.\n93373\n \n ","Department Code":"LATAM","Course Site":"<a href= 'https://www.fivecolleges.edu/courses/MHC/2015/FALL/LATAM/277/01'> Course Site </a>","Requisite":[]},"color":"rgb(162, 236, 190)","size":10.0},{"label":"LATAM-387DP","x":24.0,"y":1.0,"id":"12","attributes":{"Title":"A History of Deportation","Description":"Spring\n2015\nLatin American Studies\n387DP\nMount Holyoke College\nTaught in English, the course explores comparative racial and ethnic politics in the U.S. during the 20th century. We will analyze the creation and maintenance of structural inequalities through laws and policies targeted at persons of color in the areas of healthcare, transportation, immigration, labor, racial segregation, and education. Through readings, lectures and films, we will discuss critical histories of community struggle against social inequality, registering the central impact that race, class, gender, sexuality, and citizenship have had on efforts toward social justice. The course also offers an optional Community-Based Learning (CBL) component.\nPermission is required for interchange registration during the add/drop period only.\n91145,91138,91607\n91138\n \n ","Department Code":"LATAM","Course Site":"<a href= 'https://www.fivecolleges.edu/courses/MHC/2015/SPRING/LATAM/387DP/01'> Course Site </a>","Requisite":[]},"color":"rgb(162, 236, 190)","size":10.0},{"label":"FLMST-203","x":10.5,"y":1.0,"id":"13","attributes":{"Title":"Intro to Spanish & LatAm Film","Description":"Fall\n2015\nFilm Studies\n203\nMount Holyoke College\nThis course offers a broad introduction to the history, politics, and aesthetics of Latin American and Spanish cinema in the context of, and in contrast with, cinemas from other regions, especially hegemonic Hollywood aesthetics. This course will also focus specifically on introducing students to the basic terminology and methodologies of film analysis, thus preparing them for the department's film seminar (Spanish 320) and other advanced courses in film studies.\nPrereq: Spanish 212.\nTaught in Spanish\nPermission is required for interchange registration during the add/drop period only.\n93409,93400\n93400\n \n ","Department Code":"FLMST","Course Site":"<a href= 'https://www.fivecolleges.edu/courses/MHC/2015/FALL/FLMST/203/01'> Course Site </a>","Requisite":[]},"color":"rgb(146, 246, 89)","size":10.0},{"label":"LATIN-309","x":18.0,"y":1.0,"id":"14","attributes":{"Title":"Vergil: Aeneid","Description":"Spring\n2015\nLatin\n309\nMount Holyoke College\nA study of the Aeneid with attention both to its presentation of the classic conflict between Greek and Roman value systems and to its controversial portrayal of empire in the Augustan age.\nPrereq: Any Latin course at the 200 level or above.\nPermission is required for interchange registration during the add/drop period only.\n91143\n \n ","Department Code":"LATIN","Course Site":"<a href= 'https://www.fivecolleges.edu/courses/MHC/2015/SPRING/LATIN/309/01'> Course Site </a>","Requisite":[]},"color":"rgb(114, 171, 75)","size":10.0},{"label":"LATAM-217","x":2.0,"y":1.0,"id":"15","attributes":{"Title":"Portuguese for Span. Speakers","Description":"Fall\n2014\nLatin American Studies\n217\nMount Holyoke College\nThis course is specially designed for students who are proficient in Spanish or another Romance language. This previous knowledge will be explored to promote fast and solid acquisition of linguistic skills in Portuguese. Course conducted in Portuguese. Upon successful completion of the course, students should be able to: 1) interact with other students and the instructor in Portuguese; 2) describe and compare people, places, and things in Portuguese; 3) communicate future plans in Portuguese; 4) narrate and understand past events in Portuguese; 5) offer and understand advice and directions in Portuguese; 6) give and understand opinions in Portuguese; 7) hypothesize in Portuguese.\nPermission is required for interchange registration during the add/drop period only.\n89603,89595\n89595\n \n ","Department Code":"LATAM","Course Site":"<a href= 'https://www.fivecolleges.edu/courses/MHC/2014/FALL/LATAM/217/01'> Course Site </a>","Requisite":[]},"color":"rgb(162, 236, 190)","size":10.0},{"label":"LATAM-395","x":25.0,"y":1.0,"id":"16","attributes":{"Title":"Independent Study","Description":"Fall\n2015\nLatin American Studies\n395\nMount Holyoke College\n1.00-8.00 credits.\nPermission is required for interchange registration during all registration periods.\n94421\n \n ","Department Code":"LATAM","Course Site":"<a href= 'https://www.fivecolleges.edu/courses/MHC/2015/FALL/LATAM/395/01'> Course Site </a>","Requisite":[]},"color":"rgb(162, 236, 190)","size":10.0},{"label":"LATAM-387CL","x":26.0,"y":1.0,"id":"17","attributes":{"Title":"Chicana/Latina Lit & Thought","Description":"Fall\n2015\nLatin American Studies\n387CL\nMount Holyoke College\nCourse limited to sophomores, juniors and seniors\nPermission is required for interchange registration during the add/drop period only.\n94311,94310,94309,94388\n94310\n \n ","Department Code":"LATAM","Course Site":"<a href= 'https://www.fivecolleges.edu/courses/MHC/2015/FALL/LATAM/387CL/01'> Course Site </a>","Requisite":[]},"color":"rgb(162, 236, 190)","size":10.0},{"label":"GEOG-313","x":17.0,"y":1.0,"id":"18","attributes":{"Title":"Third World Development","Description":"Fall\n2015\nGeography\n313\nMount Holyoke College\nOffers an interdisciplinary perspective on social, economic, and political features of contemporary development in Africa, Asia, and Latin America, regions referred to as the Third World or the South, and provides an introduction to theoretical origins and definitions of economic growth, development, and underdevelopment. It then addresses more specific aspects of development such as trends in population growth, migration, and urbanization; agrarian change; livelihood strategies and aspects of social welfare such as health, education, and shelter; poverty and the environment; and external economic relationships. The latter part of the course draws extensively on selected case studies.\nThis course is open to Juniors and Seniors.; Prereq: 4 credits in department and  4 credits in related social sciences at 200 level.\nPermission is required for interchange registration during the add/drop period only.\n93248\n \n ","Department Code":"GEOG","Course Site":"<a href= 'https://www.fivecolleges.edu/courses/MHC/2015/FALL/GEOG/313/01'> Course Site </a>","Requisite":[]},"color":"rgb(215, 158, 175)","size":10.0},{"label":"LATAM-287SI","x":27.0,"y":1.0,"id":"19","attributes":{"Title":"Structural Inequalities","Description":"Spring\n2015\nLatin American Studies\n287SI\nMount Holyoke College\nThe course provides an overview of current and past social conditions of Latinas and Latinos within the U.S. We will address laws, policies and institutions that shape the complexity of Latinas'/os' social location and serve as critical sites of resistance. The course addresses legal constructions of race and citizenship, nomenclature, border politics, public health, education, and labor. We will consider the critical intersections of class, gender and sexuality as well as inequality in relation to other persons of color. Students will develop a firm sense of the importance and breadth of the Latina/o political agenda and acquire skills to think across social issues.\nPermission is required for interchange registration during the add/drop period only.\n91144,91134\n91134\n \n ","Department Code":"LATAM","Course Site":"<a href= 'https://www.fivecolleges.edu/courses/MHC/2015/SPRING/LATAM/287SI/01'> Course Site </a>","Requisite":[]},"color":"rgb(162, 236, 190)","size":10.0},{"label":"LATAM-386","x":28.0,"y":1.0,"id":"20","attributes":{"Title":"Central America: Reform, React","Description":"Fall\n2014\nLatin American Studies\n386\nMount Holyoke College\nThis seminar explores the diverse experiences of Central American nations in the twentieth century. From a common basis in an export-oriented agriculture, social and political alternatives ranging from social democracy to recurrent military rule, neofascist regimes, and revolutionary socialism have emerged in the isthmus. The course uses materials ranging from autobiography and literature to historical and anthropological studies to understand how this came to be. In addition to national cases, we consider the unique experiences of the area's indigenous and Atlantic-coast peoples within and outside the nation-state framework.\nPermission is required for interchange registration during the add/drop period only.\n88903,89055\n88903\n \n ","Department Code":"LATAM","Course Site":"<a href= 'https://www.fivecolleges.edu/courses/MHC/2014/FALL/LATAM/386/01'> Course Site </a>","Requisite":[]},"color":"rgb(162, 236, 190)","size":10.0},{"label":"LATAM-287CU","x":29.0,"y":1.0,"id":"21","attributes":{"Title":"Imagining Cuba: Hist./Memory","Description":"Spring\n2016\nLatin American Studies\n287CU\nMount Holyoke College\nThis course introduces students to critical and creative works that center Cuba and its diasporas. The primary questions of the course are: How have authors varyingly imagined Cuba over time and across space? How are these imaginings of Cuba politically, economically, and culturally situated? Students will question the personal/national and the public/private across a range of texts that explore issues of exile, nostalgia, memory, and nationalism. Readings include works by Cristina Garcia, Ana Menendez, Pablo Medina, Achy Obejas, Roberto G. Fernandez, Carmelita Tropicana, Richard Blanco, and Rachel Kushner and readings by Gustavo Perez Firmat, Sheila Croucher, and Louis A. Perez, Jr.\nPermission is required for interchange registration during the add/drop period only.\n95016,95014,95005\n95014\n \n ","Department Code":"LATAM","Course Site":"<a href= 'https://www.fivecolleges.edu/courses/MHC/2016/SPRING/LATAM/287CU/01'> Course Site </a>","Requisite":[]},"color":"rgb(162, 236, 190)","size":10.0},{"label":"ANTHR-216MA","x":30.0,"y":1.0,"id":"22","attributes":{"Title":"Maya Ethnography","Description":"Fall\n2015\nAnthropology\n216MA\nMount Holyoke College\nMaya culture has long attracted the attention of travel writers, tourists, and anthropologists. This course introduces students to historical and contemporary patterns of Maya culture through careful analysis of ethnographic texts. We will read Maya cultural formations against the historical backdrop of colonial and postcolonial Latin American history, from Spanish colonialism through the Guatemalan civil war and into the present. Discussions will cover the content of ethnographic accounts as well as the institutional and disciplinary contexts of research. The course will pay particular attention to Maya history and cosmology as intertwined fields of cultural knowledge and practice.\nPrereq: Anthropology 105.\nPermission is required for interchange registration during the add/drop period only.\n93642\n \n ","Department Code":"ANTHR","Course Site":"<a href= 'https://www.fivecolleges.edu/courses/MHC/2015/FALL/ANTHR/216MA/01'> Course Site </a>","Requisite":[]},"color":"rgb(84, 14, 195)","size":10.0},{"label":"SPAN-340CR","x":14.0,"y":1.0,"id":"23","attributes":{"Title":"Costa Rica & Lat Am New Waves","Description":"Spring\n2016\nSpanish\n340CR\nMount Holyoke College\nThis course studies the emergence of a new kind of cinematography in Costa Rica within the larger context of Latin American cinema's new waves. First, students will view and discuss several recent Latin American films in order to identify broader trends throughout the region. The focus will then turn to the specifics of a nascent brand of Costa Rican cinema that distinguishes itself from those of other Latin American countries through a unique aesthetic linked to the conditions from which they have emerged. The course will also explore how recent Costa Rican films' stylistic features address issues such as national identity.\nPrereq: Two 200-level Spanish courses above Spanish 212.\nPermission is required for interchange registration during the add/drop period only.\n95566,95565\n95566\n \n ","Department Code":"SPAN","Course Site":"<a href= 'https://www.fivecolleges.edu/courses/MHC/2016/SPRING/SPAN/340CR/01'> Course Site </a>","Requisite":[]},"color":"rgb(162, 127, 229)","size":10.0},{"label":"LATAM-260","x":31.0,"y":1.0,"id":"24","attributes":{"Title":"Afro-Latin America","Description":"Fall\n2015\nLatin American Studies\n260\nMount Holyoke College\nExploration of the history of Afro-Latin American populations since Independence within and outside the nation-state. We will question why and how to study those whose governments define them not as peoples of African descent but as part of a mixed-race majority of Hispanic cultural heritage, who themselves may often have supported this policy, and who may have had compelling reasons to avoid official scrutiny. Readings include early twentieth-century Latin American racialist theorizing; research using census, economic, criminal, and marriage records; autobiographical works, and analysis of race in textual and musical representations of peoples, regions, and nations.\nPermission is required for interchange registration during the add/drop period only.\n93376,93381,94390\n93376\n \n ","Department Code":"LATAM","Course Site":"<a href= 'https://www.fivecolleges.edu/courses/MHC/2015/FALL/LATAM/260/01'> Course Site </a>","Requisite":[]},"color":"rgb(162, 236, 190)","size":10.0},{"label":"FREN-321RL","x":13.0,"y":1.0,"id":"25","attributes":{"Title":"History of Romance Languages","Description":"Spring\n2015\nFrench\n321RL\nMount Holyoke College\nThis course examines the structural evolution of Romance languages from Vulgar Latin to contemporary forms. A chronological account will be organized around themes of persistence (inheritance from Latin) and innovation (structural change). We will begin by exploring different theories about linguistic change. Then, using concrete examples, we will analyze the main stages of development of Romance languages by focusing on different features at all linguistic levels and relating them to historical and sociological factors.\nPrereq: two of the following courses: French 215, 219, 225, or 230.\nStudents wishing to obtain 300-level credit in French must read texts and write papers in French to receive credit. This is a multimedia course where students achieve digital literacy. Technical support is provided in Audacity, Photoshop, iMovie, and iDVD\nPermission is required for interchange registration during the add/drop period only.\n91162,91252,90879,90766\n90766\n \n ","Department Code":"FREN","Course Site":"<a href= 'https://www.fivecolleges.edu/courses/MHC/2015/SPRING/FREN/321RL/01'> Course Site </a>","Requisite":[]},"color":"rgb(63, 81, 159)","size":10.0},{"label":"LATIN-102","x":21.0,"y":1.0,"id":"26","attributes":{"Title":"Elementary Latin II","Description":"Spring\n2016\nLatin\n102\nMount Holyoke College\nOffers study and practice in the grammar and syntax of classical Latin.\nPrereq: Latin 101.\nPermission is required for interchange registration during the add/drop period only.\n94754\n \n ","Department Code":"LATIN","Course Site":"<a href= 'https://www.fivecolleges.edu/courses/MHC/2016/SPRING/LATIN/102/01'> Course Site </a>","Requisite":[]},"color":"rgb(114, 171, 75)","size":10.0},{"label":"LATAM-288","x":32.0,"y":1.0,"id":"27","attributes":{"Title":"Modern Mexico","Description":"Spring\n2015\nLatin American Studies\n288\nMount Holyoke College\nAn analysis of the modern Mexican nation-state organized around three major themes: the conflictive yet symbiotic relationship with the United States, from the war of the 1840s through NAFTA most recently; the succession of reformist and revolutionary upheavals in 1810-1821, 1856-1867, 1910-1917, the 1930s, and again today, seeking to resolve both problems of the colonial past and new conflicts traceable to the very reforms generated by earlier political and social struggles; and the meaning of Mexican nationality from different ethnic, gender, and class perspectives. Readings include autobiographical and literary works, historical studies, and films.\nPermission is required for interchange registration during the add/drop period only.\n90919,91135\n91135\n \n ","Department Code":"LATAM","Course Site":"<a href= 'https://www.fivecolleges.edu/courses/MHC/2015/SPRING/LATAM/288/01'> Course Site </a>","Requisite":[]},"color":"rgb(162, 236, 190)","size":10.0},{"label":"LATIN-312","x":33.0,"y":0.0,"id":"28","attributes":{"Title":"Roma Ludens","Description":"Fall\n2014\nLatin\n312\nMount Holyoke College\nCould Romans be funny? Perhaps surprisingly, in a culture where seriousness (gravitas) and sternness (severitas) were praiseworthy attributes, Romans enjoyed theatrical productions adapted from Greek comedies - from raucous and ribald farces to more subtle comedies of manners.  They also believed that satire, poetry that poked fun at the vices and foibles of human nature, was a truly Roman genre.  Moreover, both comic and satrical elements appear in a wide range of Roman literature.  Authors may include Plautus, Terence, Horace, Ovid, Martial, Juvenal, and others.\nPermission is required for interchange registration during the add/drop period only.\n89435\n \n ","Department Code":"LATIN","Course Site":"<a href= 'https://www.fivecolleges.edu/courses/MHC/2014/FALL/LATIN/312/01'> Course Site </a>","Requisite":[]},"color":"rgb(114, 171, 75)","size":10.0},{"label":"LATIN-210","x":6.0,"y":2.0,"id":"29","attributes":{"Title":"Ovid: Metamorphoses","Description":"Spring\n2016\nLatin\n210\nMount Holyoke College\nA study of Ovid's ambitious epic celebrating change and transformative forces, with attention to the challenges it poses to traditional Roman values and to conventional Roman notions of the work appropriate to a poet. In particular, consideration will be given to the way Ovid's poem subversively responds to Vergil's work.\nPrereq: one 200- or 300-level Latin course.\nMeets with Latin 310. Three meetings per week; timing of third to be arranged with students after registration.\nPermission is required for interchange registration during the add/drop period only.\n95552\n \n ","Department Code":"LATIN","Course Site":"<a href= 'https://www.fivecolleges.edu/courses/MHC/2016/SPRING/LATIN/210/01'> Course Site </a>","Requisite":[]},"color":"rgb(114, 171, 75)","size":10.0},{"label":"LATIN-209","x":21.0,"y":3.0,"id":"30","attributes":{"Title":"Vergil: Aeneid","Description":"Spring\n2015\nLatin\n209\nMount Holyoke College\nA study of the Aeneid with attention both to its presentation of the classic conflict between Greek and Roman value systems and to its controversial portrayal of empire in the Augustan age.\nPrereq: Latin 201.\nPermission is required for interchange registration during the add/drop period only.\n91684\n \n ","Department Code":"LATIN","Course Site":"<a href= 'https://www.fivecolleges.edu/courses/MHC/2015/SPRING/LATIN/209/01'> Course Site </a>","Requisite":[]},"color":"rgb(114, 171, 75)","size":10.0},{"label":"LATIN-201","x":21.0,"y":2.0,"id":"31","attributes":{"Title":"Intermediate Latin I","Description":"Fall\n2015\nLatin\n201\nMount Holyoke College\nCombines a thorough review of Latin grammar and syntax with an introduction to the life and literature of ancient Rome, based on the reading of selected passages of Roman prose and poetry.\nPrereq: Latin 102.\nPermission is required for interchange registration during the add/drop period only.\n93004\n \n ","Department Code":"LATIN","Course Site":"<a href= 'https://www.fivecolleges.edu/courses/MHC/2015/FALL/LATIN/201/01'> Course Site </a>","Requisite":[]},"color":"rgb(114, 171, 75)","size":10.0},{"label":"LATIN-310","x":7.5,"y":1.0,"id":"32","attributes":{"Title":"Ovid: Metamorphoses","Description":"Spring\n2016\nLatin\n310\nMount Holyoke College\nA study of Ovid's ambitious epic celebrating change and transformative forces, with attention to the challenges it poses to traditional Roman values and to conventional Roman notions of the work appropriate to a poet. In particular, consideration will be given to the way Ovid's poem subversively responds to Vergil's work.\nPrereq: one 200- or 300-level Latin course.\nPermission is required for interchange registration during the add/drop period only.\n95553\n \n ","Department Code":"LATIN","Course Site":"<a href= 'https://www.fivecolleges.edu/courses/MHC/2016/SPRING/LATIN/310/01'> Course Site </a>","Requisite":[]},"color":"rgb(114, 171, 75)","size":10.0},{"label":"LATAM-287DE","x":34.0,"y":1.0,"id":"33","attributes":{"Title":"Rethinking (Under)Development","Description":"Spring\n2016\nLatin American Studies\n287DE\nMount Holyoke College\nWhen and how did the notion of 'development' emerge and spread? Why does nearly every country now aspire to it? What stigmas and hierarchies does the term 'under-development' imply? Throughout Latin America, such terms provide highly problematic not only with respect to the material reality they purport to describe but also as a framework for understanding place, time, and selfhood. In this course, students rethink conventional wisdom about 'underdevelopment' through the study of writers, filmmakers, and painters from Latin America working at different historical junctures of the twentieth century.\nPermission is required for interchange registration during the add/drop period only.\n95015,95184\n95015\n \n ","Department Code":"LATAM","Course Site":"<a href= 'https://www.fivecolleges.edu/courses/MHC/2016/SPRING/LATAM/287DE/01'> Course Site </a>","Requisite":[]},"color":"rgb(162, 236, 190)","size":10.0},{"label":"ITAL-361HS","x":8.5,"y":1.0,"id":"34","attributes":{"Title":"History of Romance Languages","Description":"Spring\n2015\nItalian\n361HS\nMount Holyoke College\nThis course examines the structural evolution of Romance languages from Vulgar Latin to contemporary forms. A chronological account will be organized around themes of persistence (inheritance from Latin) and innovation (structural change). We will begin by exploring different theories about linguistic change. Then, using concrete examples, we will analyze the main stages of development of Romance languages by focusing on different features at all linguistic levels and relating them to historical and sociological factors.\nPrereq: Two courses from 200 or 300-level, beyond ITAL-209.\nPapers will be written in English or the Romance language of the student's choice. Students wishing to obtain 300-level credit in French, Italian, or Spanish must read texts and write papers in the Romance language for which they wish to receive adva\nPermission is required for interchange registration during the add/drop period only.\n91162,91252,90879,90766\n90879\n \n ","Department Code":"ITAL","Course Site":"<a href= 'https://www.fivecolleges.edu/courses/MHC/2015/SPRING/ITAL/361HS/01'> Course Site </a>","Requisite":[]},"color":"rgb(226, 157, 97)","size":10.0},{"label":"SPAN-360RL","x":15.0,"y":1.0,"id":"35","attributes":{"Title":"History of Romance Languages","Description":"Spring\n2015\nSpanish\n360RL\nMount Holyoke College\nThis course examines the structural evolution of Romance languages from Vulgar Latin to contemporary forms. A chronological account will be organized around themes of persistence (inheritance from Latin) and innovation (structural change). We will begin by exploring different theories about linguistic change. Then, using concrete examples, we will analyze the main stages of development of Romance languages by focusing on different features at all linguistic levels and relating them to historical and sociological factors.\nPrereq: Two 200-level courses above Spanish 212.\nPapers will be written in English or the Romance language of the student's choice. Students wishing to obtain 300-level credit in French, Italian, or Spanish must read texts and write papers in the Romance language for which they wish to receive adva\nPermission is required for interchange registration during the add/drop period only.\n91162,91252,90879,90766\n91252\n \n ","Department Code":"SPAN","Course Site":"<a href= 'https://www.fivecolleges.edu/courses/MHC/2015/SPRING/SPAN/360RL/01'> Course Site </a>","Requisite":[]},"color":"rgb(162, 127, 229)","size":10.0},{"label":"LATIN-101","x":21.0,"y":0.0,"id":"36","attributes":{"Title":"Elementary Latin I","Description":"Fall\n2015\nLatin\n101\nMount Holyoke College\nOffers study and practice in the grammar and syntax of classical Latin.\nThis course is limited to first years, sophomores and juniors\nPermission is required for interchange registration during the add/drop period only.\n93002\n \n ","Department Code":"LATIN","Course Site":"<a href= 'https://www.fivecolleges.edu/courses/MHC/2015/FALL/LATIN/101/01'> Course Site </a>","Requisite":[]},"color":"rgb(114, 171, 75)","size":10.0},{"label":"FLMST-370CR","x":3.5,"y":1.0,"id":"37","attributes":{"Title":"Costa Rica & Lat Am New Waves","Description":"Spring\n2016\nFilm Studies\n370CR\nMount Holyoke College\nThis course studies the emergence of a new kind of cinematography in Costa Rica within the larger context of Latin American cinema's new waves. First, students will view and discuss several recent Latin American films in order to identify broader trends throughout the region. The focus will then turn to the specifics of a nascent brand of Costa Rican cinema that distinguishes itself from those of other Latin American countries through a unique aesthetic linked to the conditions from which they have emerged. The course will also explore how recent Costa Rican films' stylistic features address issues such as national identity.\nPrereq: Two 200-level Spanish courses above Spanish 212.\nTaught in Spanish\nPermission is required for interchange registration during the add/drop period only.\n95566,95565\n95565\n \n ","Department Code":"FLMST","Course Site":"<a href= 'https://www.fivecolleges.edu/courses/MHC/2016/SPRING/FLMST/370CR/01'> Course Site </a>","Requisite":[]},"color":"rgb(146, 246, 89)","size":10.0},{"label":"LATIN-388","x":0.0,"y":0.0,"id":"38","attributes":{"Title":"LATIN-388","Description":"not offered in the last 4 semesters","Department Code":"LATIN","Course Site":"","Requisite":""},"color":"rgb(114, 171, 75)","size":10.0},{"label":"LATIN-227","x":1.0,"y":0.0,"id":"39","attributes":{"Title":"LATIN-227","Description":"not offered in the last 4 semesters","Department Code":"LATIN","Course Site":"","Requisite":""},"color":"rgb(114, 171, 75)","size":10.0},{"label":"LATIN-217","x":2.0,"y":0.0,"id":"40","attributes":{"Title":"LATIN-217","Description":"not offered in the last 4 semesters","Department Code":"LATIN","Course Site":"","Requisite":""},"color":"rgb(114, 171, 75)","size":10.0},{"label":"LATIN-287RC","x":3.0,"y":0.0,"id":"41","attributes":{"Title":"LATIN-287RC","Description":"not offered in the last 4 semesters","Department Code":"LATIN","Course Site":"","Requisite":""},"color":"rgb(114, 171, 75)","size":10.0},{"label":"LATIN-387CM","x":4.0,"y":0.0,"id":"42","attributes":{"Title":"LATIN-387CM","Description":"not offered in the last 4 semesters","Department Code":"LATIN","Course Site":"","Requisite":""},"color":"rgb(114, 171, 75)","size":10.0},{"label":"LATIN-200","x":9.0,"y":0.0,"id":"43","attributes":{"Title":"LATIN-200","Description":"not offered in the last 4 semesters","Department Code":"LATIN","Course Site":"","Requisite":""},"color":"rgb(114, 171, 75)","size":10.0},{"label":"LATIN-180","x":20.0,"y":0.0,"id":"44","attributes":{"Title":"LATIN-180","Description":"not offered in the last 4 semesters","Department Code":"LATIN","Course Site":"","Requisite":""},"color":"rgb(114, 171, 75)","size":10.0},{"label":"LATIN-212","x":13.5,"y":0.0,"id":"45","attributes":{"Title":"LATIN-212","Description":"not offered in the last 4 semesters","Department Code":"LATIN","Course Site":"","Requisite":""},"color":"rgb(114, 171, 75)","size":10.0},{"label":"LATIN-200","x":35.0,"y":0.0,"id":"46","attributes":{"Title":"LATIN-200","Description":"not offered in the last 4 semesters","Department Code":"LATIN","Course Site":"","Requisite":""},"color":"rgb(114, 171, 75)","size":10.0},{"label":"LATIN-300","x":5.5,"y":0.0,"id":"47","attributes":{"Title":"LATIN-300","Description":"not offered in the last 4 semesters","Department Code":"LATIN","Course Site":"","Requisite":""},"color":"rgb(114, 171, 75)","size":10.0},{"label":"LATIN-300","x":36.0,"y":0.0,"id":"48","attributes":{"Title":"LATIN-300","Description":"not offered in the last 4 semesters","Department Code":"LATIN","Course Site":"","Requisite":""},"color":"rgb(114, 171, 75)","size":10.0},{"label":"LATIN-100","x":22.0,"y":0.0,"id":"49","attributes":{"Title":"LATIN-100","Description":"not offered in the last 4 semesters","Department Code":"LATIN","Course Site":"","Requisite":""},"color":"rgb(114, 171, 75)","size":10.0},{"label":"LATIN-277","x":23.0,"y":0.0,"id":"50","attributes":{"Title":"LATIN-277","Description":"not offered in the last 4 semesters","Department Code":"LATIN","Course Site":"","Requisite":""},"color":"rgb(114, 171, 75)","size":10.0},{"label":"LATIN-387DP","x":24.0,"y":0.0,"id":"51","attributes":{"Title":"LATIN-387DP","Description":"not offered in the last 4 semesters","Department Code":"LATIN","Course Site":"","Requisite":""},"color":"rgb(114, 171, 75)","size":10.0},{"label":"LATIN-212","x":37.0,"y":0.0,"id":"52","attributes":{"Title":"LATIN-212","Description":"not offered in the last 4 semesters","Department Code":"LATIN","Course Site":"","Requisite":""},"color":"rgb(114, 171, 75)","size":10.0},{"label":"LATIN-200","x":38.0,"y":0.0,"id":"53","attributes":{"Title":"LATIN-200","Description":"not offered in the last 4 semesters","Department Code":"LATIN","Course Site":"","Requisite":""},"color":"rgb(114, 171, 75)","size":10.0},{"label":"LATIN-217","x":39.0,"y":0.0,"id":"54","attributes":{"Title":"LATIN-217","Description":"not offered in the last 4 semesters","Department Code":"LATIN","Course Site":"","Requisite":""},"color":"rgb(114, 171, 75)","size":10.0},{"label":"LATIN-395","x":25.0,"y":0.0,"id":"55","attributes":{"Title":"LATIN-395","Description":"not offered in the last 4 semesters","Department Code":"LATIN","Course Site":"","Requisite":""},"color":"rgb(114, 171, 75)","size":10.0},{"label":"LATIN-387CL","x":26.0,"y":0.0,"id":"56","attributes":{"Title":"LATIN-387CL","Description":"not offered in the last 4 semesters","Department Code":"LATIN","Course Site":"","Requisite":""},"color":"rgb(114, 171, 75)","size":10.0},{"label":"LATIN-200","x":40.0,"y":0.0,"id":"57","attributes":{"Title":"LATIN-200","Description":"not offered in the last 4 semesters","Department Code":"LATIN","Course Site":"","Requisite":""},"color":"rgb(114, 171, 75)","size":10.0},{"label":"LATIN-287SI","x":27.0,"y":0.0,"id":"58","attributes":{"Title":"LATIN-287SI","Description":"not offered in the last 4 semesters","Department Code":"LATIN","Course Site":"","Requisite":""},"color":"rgb(114, 171, 75)","size":10.0},{"label":"LATIN-386","x":28.0,"y":0.0,"id":"59","attributes":{"Title":"LATIN-386","Description":"not offered in the last 4 semesters","Department Code":"LATIN","Course Site":"","Requisite":""},"color":"rgb(114, 171, 75)","size":10.0},{"label":"LATIN-287CU","x":29.0,"y":0.0,"id":"60","attributes":{"Title":"LATIN-287CU","Description":"not offered in the last 4 semesters","Department Code":"LATIN","Course Site":"","Requisite":""},"color":"rgb(114, 171, 75)","size":10.0},{"label":"LATIN-105","x":30.0,"y":0.0,"id":"61","attributes":{"Title":"LATIN-105","Description":"not offered in the last 4 semesters","Department Code":"LATIN","Course Site":"","Requisite":""},"color":"rgb(114, 171, 75)","size":10.0},{"label":"LATIN-200","x":41.0,"y":0.0,"id":"62","attributes":{"Title":"LATIN-200","Description":"not offered in the last 4 semesters","Department Code":"LATIN","Course Site":"","Requisite":""},"color":"rgb(114, 171, 75)","size":10.0},{"label":"LATIN-212","x":42.0,"y":0.0,"id":"63","attributes":{"Title":"LATIN-212","Description":"not offered in the last 4 semesters","Department Code":"LATIN","Course Site":"","Requisite":""},"color":"rgb(114, 171, 75)","size":10.0},{"label":"LATIN-260","x":31.0,"y":0.0,"id":"64","attributes":{"Title":"LATIN-260","Description":"not offered in the last 4 semesters","Department Code":"LATIN","Course Site":"","Requisite":""},"color":"rgb(114, 171, 75)","size":10.0},{"label":"LATIN-215","x":14.5,"y":0.0,"id":"65","attributes":{"Title":"LATIN-215","Description":"not offered in the last 4 semesters","Department Code":"LATIN","Course Site":"","Requisite":""},"color":"rgb(114, 171, 75)","size":10.0},{"label":"LATIN-219","x":16.5,"y":0.0,"id":"66","attributes":{"Title":"LATIN-219","Description":"not offered in the last 4 semesters","Department Code":"LATIN","Course Site":"","Requisite":""},"color":"rgb(114, 171, 75)","size":10.0},{"label":"LATIN-225","x":17.5,"y":0.0,"id":"67","attributes":{"Title":"LATIN-225","Description":"not offered in the last 4 semesters","Department Code":"LATIN","Course Site":"","Requisite":""},"color":"rgb(114, 171, 75)","size":10.0},{"label":"LATIN-230","x":15.5,"y":0.0,"id":"68","attributes":{"Title":"LATIN-230","Description":"not offered in the last 4 semesters","Department Code":"LATIN","Course Site":"","Requisite":""},"color":"rgb(114, 171, 75)","size":10.0},{"label":"LATIN-300","x":43.0,"y":0.0,"id":"69","attributes":{"Title":"LATIN-300","Description":"not offered in the last 4 semesters","Department Code":"LATIN","Course Site":"","Requisite":""},"color":"rgb(114, 171, 75)","size":10.0},{"label":"LATIN-288","x":32.0,"y":0.0,"id":"70","attributes":{"Title":"LATIN-288","Description":"not offered in the last 4 semesters","Department Code":"LATIN","Course Site":"","Requisite":""},"color":"rgb(114, 171, 75)","size":10.0},{"label":"LATIN-200","x":44.0,"y":0.0,"id":"71","attributes":{"Title":"LATIN-200","Description":"not offered in the last 4 semesters","Department Code":"LATIN","Course Site":"","Requisite":""},"color":"rgb(114, 171, 75)","size":10.0},{"label":"LATIN-300","x":45.0,"y":0.0,"id":"72","attributes":{"Title":"LATIN-300","Description":"not offered in the last 4 semesters","Department Code":"LATIN","Course Site":"","Requisite":""},"color":"rgb(114, 171, 75)","size":10.0},{"label":"LATIN-200","x":46.0,"y":0.0,"id":"73","attributes":{"Title":"LATIN-200","Description":"not offered in the last 4 semesters","Department Code":"LATIN","Course Site":"","Requisite":""},"color":"rgb(114, 171, 75)","size":10.0},{"label":"LATIN-300","x":47.0,"y":0.0,"id":"74","attributes":{"Title":"LATIN-300","Description":"not offered in the last 4 semesters","Department Code":"LATIN","Course Site":"","Requisite":""},"color":"rgb(114, 171, 75)","size":10.0},{"label":"LATIN-287DE","x":34.0,"y":0.0,"id":"75","attributes":{"Title":"LATIN-287DE","Description":"not offered in the last 4 semesters","Department Code":"LATIN","Course Site":"","Requisite":""},"color":"rgb(114, 171, 75)","size":10.0},{"label":"LATIN-200","x":48.0,"y":0.0,"id":"76","attributes":{"Title":"LATIN-200","Description":"not offered in the last 4 semesters","Department Code":"LATIN","Course Site":"","Requisite":""},"color":"rgb(114, 171, 75)","size":10.0},{"label":"LATIN-300","x":49.0,"y":0.0,"id":"77","attributes":{"Title":"LATIN-300","Description":"not offered in the last 4 semesters","Department Code":"LATIN","Course Site":"","Requisite":""},"color":"rgb(114, 171, 75)","size":10.0},{"label":"LATIN-200","x":50.0,"y":0.0,"id":"78","attributes":{"Title":"LATIN-200","Description":"not offered in the last 4 semesters","Department Code":"LATIN","Course Site":"","Requisite":""},"color":"rgb(114, 171, 75)","size":10.0},{"label":"LATIN-212","x":51.0,"y":0.0,"id":"79","attributes":{"Title":"LATIN-212","Description":"not offered in the last 4 semesters","Department Code":"LATIN","Course Site":"","Requisite":""},"color":"rgb(114, 171, 75)","size":10.0},{"label":"LATIN-300","x":52.0,"y":0.0,"id":"80","attributes":{"Title":"LATIN-300","Description":"not offered in the last 4 semesters","Department Code":"LATIN","Course Site":"","Requisite":""},"color":"rgb(114, 171, 75)","size":10.0},{"label":"LATIN-200","x":53.0,"y":0.0,"id":"81","attributes":{"Title":"LATIN-200","Description":"not offered in the last 4 semesters","Department Code":"LATIN","Course Site":"","Requisite":""},"color":"rgb(114, 171, 75)","size":10.0},{"label":"LATIN-212","x":54.0,"y":0.0,"id":"82","attributes":{"Title":"LATIN-212","Description":"not offered in the last 4 semesters","Department Code":"LATIN","Course Site":"","Requisite":""},"color":"rgb(114, 171, 75)","size":10.0}]}