{"edges":[{"label":"","source":"0","target":"0","id":"6","attributes":{},"color":"rgb(236, 69, 118)","size":1.0},{"label":"","source":"1","target":"1","id":"8","attributes":{},"color":"rgb(236, 69, 118)","size":1.0},{"label":"","source":"2","target":"2","id":"10","attributes":{},"color":"rgb(236, 69, 118)","size":1.0},{"label":"","source":"3","target":"3","id":"12","attributes":{},"color":"rgb(236, 69, 118)","size":1.0},{"label":"","source":"4","target":"4","id":"14","attributes":{},"color":"rgb(126, 83, 86)","size":1.0},{"label":"","source":"4","target":"19","id":"16","attributes":{},"color":"rgb(236, 69, 118)","size":1.0},{"label":"","source":"5","target":"5","id":"18","attributes":{},"color":"rgb(236, 69, 118)","size":1.0},{"label":"","source":"6","target":"6","id":"20","attributes":{},"color":"rgb(236, 69, 118)","size":1.0},{"label":"","source":"7","target":"7","id":"22","attributes":{},"color":"rgb(236, 69, 118)","size":1.0},{"label":"","source":"7","target":"9","id":"24","attributes":{},"color":"rgb(186, 21, 128)","size":1.0},{"label":"","source":"8","target":"8","id":"26","attributes":{},"color":"rgb(236, 69, 118)","size":1.0},{"label":"","source":"9","target":"7","id":"28","attributes":{},"color":"rgb(236, 69, 118)","size":1.0},{"label":"","source":"9","target":"9","id":"30","attributes":{},"color":"rgb(186, 21, 128)","size":1.0},{"label":"","source":"10","target":"10","id":"32","attributes":{},"color":"rgb(236, 69, 118)","size":1.0},{"label":"","source":"10","target":"28","id":"34","attributes":{},"color":"rgb(236, 69, 118)","size":1.0},{"label":"","source":"11","target":"11","id":"36","attributes":{},"color":"rgb(236, 69, 118)","size":1.0},{"label":"","source":"12","target":"1","id":"38","attributes":{},"color":"rgb(236, 69, 118)","size":1.0},{"label":"","source":"12","target":"11","id":"40","attributes":{},"color":"rgb(236, 69, 118)","size":1.0},{"label":"","source":"12","target":"12","id":"42","attributes":{},"color":"rgb(236, 69, 118)","size":1.0},{"label":"","source":"12","target":"12","id":"44","attributes":{},"color":"rgb(236, 69, 118)","size":1.0},{"label":"","source":"12","target":"25","id":"46","attributes":{},"color":"rgb(236, 69, 118)","size":1.0},{"label":"","source":"13","target":"13","id":"48","attributes":{},"color":"rgb(236, 69, 118)","size":1.0},{"label":"","source":"13","target":"13","id":"50","attributes":{},"color":"rgb(236, 69, 118)","size":1.0},{"label":"","source":"13","target":"27","id":"52","attributes":{},"color":"rgb(69, 144, 77)","size":1.0},{"label":"","source":"14","target":"14","id":"54","attributes":{},"color":"rgb(236, 69, 118)","size":1.0},{"label":"","source":"15","target":"15","id":"56","attributes":{},"color":"rgb(236, 69, 118)","size":1.0},{"label":"","source":"15","target":"28","id":"58","attributes":{},"color":"rgb(236, 69, 118)","size":1.0},{"label":"","source":"16","target":"16","id":"60","attributes":{},"color":"rgb(236, 69, 118)","size":1.0},{"label":"","source":"16","target":"28","id":"62","attributes":{},"color":"rgb(236, 69, 118)","size":1.0},{"label":"","source":"17","target":"13","id":"64","attributes":{},"color":"rgb(236, 69, 118)","size":1.0},{"label":"","source":"17","target":"17","id":"66","attributes":{},"color":"rgb(69, 144, 77)","size":1.0},{"label":"","source":"18","target":"18","id":"68","attributes":{},"color":"rgb(236, 69, 118)","size":1.0},{"label":"","source":"19","target":"19","id":"70","attributes":{},"color":"rgb(236, 69, 118)","size":1.0},{"label":"","source":"20","target":"20","id":"72","attributes":{},"color":"rgb(236, 69, 118)","size":1.0},{"label":"","source":"21","target":"21","id":"74","attributes":{},"color":"rgb(236, 69, 118)","size":1.0},{"label":"","source":"22","target":"22","id":"76","attributes":{},"color":"rgb(236, 69, 118)","size":1.0},{"label":"","source":"23","target":"23","id":"78","attributes":{},"color":"rgb(236, 69, 118)","size":1.0},{"label":"","source":"24","target":"24","id":"80","attributes":{},"color":"rgb(236, 69, 118)","size":1.0},{"label":"","source":"25","target":"25","id":"82","attributes":{},"color":"rgb(236, 69, 118)","size":1.0},{"label":"","source":"26","target":"26","id":"84","attributes":{},"color":"rgb(236, 69, 118)","size":1.0},{"label":"","source":"27","target":"13","id":"86","attributes":{},"color":"rgb(236, 69, 118)","size":1.0},{"label":"","source":"27","target":"13","id":"88","attributes":{},"color":"rgb(236, 69, 118)","size":1.0},{"label":"","source":"27","target":"13","id":"90","attributes":{},"color":"rgb(236, 69, 118)","size":1.0},{"label":"","source":"27","target":"27","id":"92","attributes":{},"color":"rgb(69, 144, 77)","size":1.0},{"label":"","source":"28","target":"28","id":"94","attributes":{},"color":"rgb(236, 69, 118)","size":1.0},{"label":"","source":"29","target":"29","id":"96","attributes":{},"color":"rgb(236, 69, 118)","size":1.0},{"label":"","source":"30","target":"10","id":"98","attributes":{},"color":"rgb(236, 69, 118)","size":1.0},{"label":"","source":"30","target":"16","id":"100","attributes":{},"color":"rgb(236, 69, 118)","size":1.0},{"label":"","source":"30","target":"24","id":"102","attributes":{},"color":"rgb(236, 69, 118)","size":1.0},{"label":"","source":"31","target":"0","id":"104","attributes":{},"color":"rgb(236, 69, 118)","size":1.0},{"label":"","source":"32","target":"10","id":"106","attributes":{},"color":"rgb(236, 69, 118)","size":1.0},{"label":"","source":"32","target":"10","id":"108","attributes":{},"color":"rgb(236, 69, 118)","size":1.0},{"label":"","source":"32","target":"24","id":"110","attributes":{},"color":"rgb(236, 69, 118)","size":1.0},{"label":"","source":"32","target":"24","id":"112","attributes":{},"color":"rgb(236, 69, 118)","size":1.0},{"label":"","source":"33","target":"10","id":"114","attributes":{},"color":"rgb(236, 69, 118)","size":1.0},{"label":"","source":"33","target":"24","id":"116","attributes":{},"color":"rgb(236, 69, 118)","size":1.0},{"label":"","source":"33","target":"24","id":"118","attributes":{},"color":"rgb(236, 69, 118)","size":1.0},{"label":"","source":"34","target":"5","id":"120","attributes":{},"color":"rgb(236, 69, 118)","size":1.0},{"label":"","source":"34","target":"10","id":"122","attributes":{},"color":"rgb(236, 69, 118)","size":1.0},{"label":"","source":"34","target":"19","id":"124","attributes":{},"color":"rgb(236, 69, 118)","size":1.0},{"label":"","source":"34","target":"21","id":"126","attributes":{},"color":"rgb(236, 69, 118)","size":1.0},{"label":"","source":"34","target":"26","id":"128","attributes":{},"color":"rgb(236, 69, 118)","size":1.0},{"label":"","source":"34","target":"28","id":"130","attributes":{},"color":"rgb(236, 69, 118)","size":1.0},{"label":"","source":"34","target":"29","id":"132","attributes":{},"color":"rgb(236, 69, 118)","size":1.0},{"label":"","source":"35","target":"12","id":"134","attributes":{},"color":"rgb(236, 69, 118)","size":1.0},{"label":"","source":"35","target":"15","id":"136","attributes":{},"color":"rgb(236, 69, 118)","size":1.0},{"label":"","source":"35","target":"16","id":"138","attributes":{},"color":"rgb(236, 69, 118)","size":1.0},{"label":"","source":"36","target":"20","id":"140","attributes":{},"color":"rgb(236, 69, 118)","size":1.0}],"nodes":[{"label":"FRN-385","x":0.0,"y":1.0,"id":"0","attributes":{"Title":"ADV STUDIES IN LANGUAGE","Description":"Spring\n2016\nFrench\n385\nSmith College\nTopics Course. An overview of commercial and financial terminology against the backdrop of contemporary French business culture, using case studies, French television and newspapers, and the internet. Emphasis on essential technical vocabulary, reading and writing business documents, and oral communication in a business setting. Prepares students for the Diplome de francais professionnel (Affaires B2) granted by the Paris Chamber of Commerce and Industry and administered at Smith College. Prerequisite: a 300-level French course, a solid foundation in grammar, and excellent command of everyday vocabulary or permission of the instructor.\nTopic: Global French - The Language of Business and International Trade.\nPermission is required for interchange registration during the add/drop period only.\n41457-S16\n \n ","Department Code":"FRN","Course Site":"<a href= 'https://www.fivecolleges.edu/courses/SC/2016/SPRING/FRN/385/01'> Course Site </a>","Requisite":["Topics Course. An overview of commercial and financial terminology against the backdrop of contemporary French business culture, using case studies, French television and newspapers, and the internet. Emphasis on essential technical vocabulary, reading and writing business documents, and oral communication in a business setting. Prepares students for the Diplome de francais professionnel (Affaires B2) granted by the Paris Chamber of Commerce and Industry and administered at Smith College. Prerequisite: a 300-level French course, a solid foundation in grammar, and excellent command of everyday vocabulary or permission of the instructor."]},"color":"rgb(236, 69, 118)","size":10.0},{"label":"FRN-265","x":1.0,"y":2.0,"id":"1","attributes":{"Title":"LES ANNEES NOIRES, 1939-45","Description":"Fall\n2014\nFrench\n265\nSmith College\nWhat was it like to live in Paris under the German occupation? What were the moral dilemmas and the political risks that Parisians faced as they struggled to survive? And how are we, today, to judge this historical period and those who lived through it? Students will experience this difficult period through a global simulation in which each will create a character with a specific identity and past?a secret collaborator, a Jewish immigrant, a resistance fighter, a closeted homosexual, an avant-garde artist, a reporter, the widow of a soldier who fought under Marechal Petain in WWI?and representing the diversity of the Parisian population at the time. Each student will write her character?s \"memoirs\" reacting to historical as well as personal events from her unique perspective. Readings range from historical documents, speeches, and testimonials to drama, fiction. Weekly films. Prerequisite: FRN 230. Enrollment limited to 16. WI (in French)\nPermission is required for interchange registration during the add/drop period only.\n19866-F14\n \n ","Department Code":"FRN","Course Site":"<a href= 'https://www.fivecolleges.edu/courses/SC/2014/FALL/FRN/265/01'> Course Site </a>","Requisite":["What was it like to live in Paris under the German occupation? What were the moral dilemmas and the political risks that Parisians faced as they struggled to survive? And how are we, today, to judge this historical period and those who lived through it? Students will experience this difficult period through a global simulation in which each will create a character with a specific identity and past?a secret collaborator, a Jewish immigrant, a resistance fighter, a closeted homosexual, an avant-garde artist, a reporter, the widow of a soldier who fought under Marechal Petain in WWI?and representing the diversity of the Parisian population at the time. Each student will write her character?s \"memoirs\" reacting to historical as well as personal events from her unique perspective. Readings range from historical documents, speeches, and testimonials to drama, fiction. Weekly films. Prerequisite: FRN 230. Enrollment limited to 16. WI (in French)"]},"color":"rgb(236, 69, 118)","size":10.0},{"label":"FRN-580D","x":11.5,"y":0.0,"id":"2","attributes":{"Title":"ADVANCED STUDIES","Description":"Spring\n2016\nFrench\n580D\nSmith College\nThis is a full-year course.\n, Limited to graduate students\nPermission is required for interchange registration during the add/drop period only.\n30453-S16\n \n ","Department Code":"FRN","Course Site":"<a href= 'https://www.fivecolleges.edu/courses/SC/2016/SPRING/FRN/580D/0'> Course Site </a>","Requisite":[]},"color":"rgb(236, 69, 118)","size":10.0},{"label":"FRN-365","x":12.5,"y":0.0,"id":"3","attributes":{"Title":"FRANCOPHONE LIT & CULTURE","Description":"Fall\n2015\nFrench\n365\nSmith College\nTopics course. How much control does or should a writer have over his or her public image? Should artists be held responsible for the political or social consequences of their work? How do such questions as censorship and plagiarism play out when racial, religious or sexual difference is at stake? This course examines literary texts and essays by some of the more controversial names in contemporary Francophone literature, to be studied alongside films, interviews, television appearances, and critical and popular reviews. Works by Calixthe Beyala, Rachid Bouchareb, Maryse Conde and Dany Laferriere.\nTopic: Scandals and Spin Control: Francophone Literature in the Media.\nPermission is required for interchange registration during the add/drop period only.\n20867-F15\n \n ","Department Code":"FRN","Course Site":"<a href= 'https://www.fivecolleges.edu/courses/SC/2015/FALL/FRN/365/01'> Course Site </a>","Requisite":[]},"color":"rgb(236, 69, 118)","size":10.0},{"label":"THE-252","x":9.5,"y":0.0,"id":"4","attributes":{"Title":"SET DESIGN I","Description":"Fall\n2015\nTheatre\n252\nSmith College\nThe course develops overall design skills for designing sets for the theatre. After reading assigned plays, students learn to develop their designs by concentrating on character analysis and visualizing the action of the play. Visual research, sketches, basic drafting skills and model building are some of the areas in which students learn to develop their ideas. This course also emphasizes the importance of collaborating with every member of the creative team. Enrollment limited to 12.\nPermission is required for interchange registration during the add/drop period only.\n20949-F15\n \n ","Department Code":"THE","Course Site":"<a href= 'https://www.fivecolleges.edu/courses/SC/2015/FALL/THE/252/01'> Course Site </a>","Requisite":[]},"color":"rgb(126, 83, 86)","size":10.0},{"label":"FRN-250","x":3.0,"y":1.0,"id":"5","attributes":{"Title":"SKYPING WITH THE FRENCH","Description":"Spring\n2016\nFrench\n250\nSmith College\nUsing webcam and videoconferencing technology, students have conversations in real time with French students in Paris. We examine youth culture in France and explore fundamental cultural differences between Americans and the French. Topics include cultural attitudes and beliefs, social values and institutions as well as relevant socioeconomic issues. Materials: textbooks, cultural essays, surveys, articles, films and songs. Prerequisite: 230 or higher or permission of the instructor. Enrollment limited to 15.\nPermission is required for interchange registration during the add/drop period only.\n38495-S16\n \n ","Department Code":"FRN","Course Site":"<a href= 'https://www.fivecolleges.edu/courses/SC/2016/SPRING/FRN/250/01'> Course Site </a>","Requisite":["Using webcam and videoconferencing technology, students have conversations in real time with French students in Paris. We examine youth culture in France and explore fundamental cultural differences between Americans and the French. Topics include cultural attitudes and beliefs, social values and institutions as well as relevant socioeconomic issues. Materials: textbooks, cultural essays, surveys, articles, films and songs. Prerequisite: 230 or higher or permission of the instructor. Enrollment limited to 15."]},"color":"rgb(236, 69, 118)","size":10.0},{"label":"FRN-340","x":13.5,"y":0.0,"id":"6","attributes":{"Title":"TOPICS IN 17TH/18TH CENT LIT","Description":"Spring\n2016\nFrench\n340\nSmith College\nTopics course. How did social networks connect people who shared common interests and activities in early modern France? What defines the so-called French sociability and how does it emerge in both court and town society in the early 17th-century? We look at theater as a place of civil interchange, the academies, the salons, private correspondences, among other social spaces,\u00a0to understand how social networks played an integral role in the production of knowledge and the process of Enlightenment to better understand how the social life of the past has come to shape the contours of the present.\nTopic: Social Networking in Early Modern France.\nPermission is required for interchange registration during the add/drop period only.\n41455-S16\n \n ","Department Code":"FRN","Course Site":"<a href= 'https://www.fivecolleges.edu/courses/SC/2016/SPRING/FRN/340/01'> Course Site </a>","Requisite":[]},"color":"rgb(236, 69, 118)","size":10.0},{"label":"FRN-290","x":14.5,"y":1.0,"id":"7","attributes":{"Title":"COLONIAL CITY: GLOBAL PRSPCTVS","Description":"Spring\n2016\nFrench\n290\nSmith College\nSame as ARH 258. This class examines the architectural history of French colonialism from a global historical perspective. French colonialism marked the longest episode of French interaction with the non-European world. This class encourages a broader understanding of its architectural impact through approaching the buildings, towns and cities that emerged during French imperialism. We engage colonial iterations of \"high style,\" or official, governmental architecture, in addition to examining vernacular forms engendered because of the blending of building traditions. We consider sites in Africa, North America, the Caribbean, Asia and the Indian Ocean. We think through the social and economic factors that caused architectural and urban typologies to display marked continuities despite geographical distinctions.\nPermission is required for interchange registration during the add/drop period only.\n41357\n41358-S16\n \n ","Department Code":"FRN","Course Site":"<a href= 'https://www.fivecolleges.edu/courses/SC/2016/SPRING/FRN/290/01'> Course Site </a>","Requisite":[]},"color":"rgb(236, 69, 118)","size":10.0},{"label":"FRN-363","x":15.5,"y":0.0,"id":"8","attributes":{"Title":"ROMANCE & ROM NOVL 19TH C FRN","Description":"Spring\n2015\nFrench\n363\nSmith College\nOne of the most ancient and universal feelings, love is also infinitely elusive and as much about the self as it is about anything else. In this course, intended for literary as well as nonliterary students, we examine what the romantic imagination has made of the mystery, magic and travails of love, and how it confronted some of the major cultural and social issues of its time: marriage and happiness, exoticism, class divide, love and death. Novels by Bernardin de Saint-Pierre, Chateaubriand, George Sand, Lamartine, Alexandre Dumas and Nerval.\nPermission is required for interchange registration during the add/drop period only.\n40968-S15\n \n ","Department Code":"FRN","Course Site":"<a href= 'https://www.fivecolleges.edu/courses/SC/2015/SPRING/FRN/363/01'> Course Site </a>","Requisite":[]},"color":"rgb(236, 69, 118)","size":10.0},{"label":"ARH-258","x":14.5,"y":0.0,"id":"9","attributes":{"Title":"COLONIAL CITY: GLOBAL PRSPCTVS","Description":"Spring\n2016\nArt History\n258\nSmith College\nSame as FRN 290. This class examines the architectural history of French colonialism from a global historical perspective. French colonialism marked the longest episode of French interaction with the non-European world. This class encourages a broader understanding of its architectural impact through approaching the buildings, towns, and cities that emerged during French imperialism. We engage colonial iterations of \"high style,\" or official, governmental architecture, in addition to examining vernacular forms engendered because of the blending of building traditions. We consider sites in Africa, North America, the Caribbean, Asia and the Indian Ocean. We think through the social and economic factors that caused architectural and urban typologies to display marked continuities despite geographical distinctions. Group B (E)\nPermission is required for interchange registration during the add/drop period only.\n41358\n41357-S16\n \n ","Department Code":"ARH","Course Site":"<a href= 'https://www.fivecolleges.edu/courses/SC/2016/SPRING/ARH/258/01'> Course Site </a>","Requisite":[]},"color":"rgb(186, 21, 128)","size":10.0},{"label":"FRN-103","x":8.0,"y":1.0,"id":"10","attributes":{"Title":"INTENSIVE INTERMEDIATE FRENCH","Description":"Spring\n2016\nFrench\n103\nSmith College\nThis course uses the same textbooks as 102, at a faster pace and with additional work on reading, writing and oral skills; special attention to composition and building vocabulary. Additional materials include websites, podcasts, works by Colette, Maupassant, Sartre and others. Prerequisite: 101. Students completing the course may be eligible to enter 230. Students who take 102 may not take 103. Admission only by permission of the instructor.\nInstructor permission.\nPermission is required for interchange registration during all registration periods.\n39901-S16\n \n ","Department Code":"FRN","Course Site":"<a href= 'https://www.fivecolleges.edu/courses/SC/2016/SPRING/FRN/103/01'> Course Site </a>","Requisite":["This course uses the same textbooks as 102, at a faster pace and with additional work on reading, writing and oral skills; special attention to composition and building vocabulary. Additional materials include websites, podcasts, works by Colette, Maupassant, Sartre and others. Prerequisite: 101. Students completing the course may be eligible to enter 230. Students who take 102 may not take 103. Admission only by permission of the instructor."]},"color":"rgb(236, 69, 118)","size":10.0},{"label":"FRN-282","x":2.0,"y":2.0,"id":"11","attributes":{"Title":"TOPICS/19TH & 20TH C FRN STUDY","Description":"Spring\n2015\nFrench\n282\nSmith College\nTopics course. How do stories about moral dilemmas frame the question of what is right and what is wrong? What do these stories say about the values that are at stake? Do they provide answers and, if so, which ones? By investigating how stories revolving around moral conflicts reproduce social, cultural and political contradictions, as well as ethical ones, this course allows students to reflect on some of the major issues that have shaped the moral debate in post-revolutionary France. Readings by Balzac, Hugo, Zola, Gide, Camus, Sartre and Benameur. Prerequisite: one course above FRN 230.\nTopic: What's right? What's wrong? Stories about moral dilemmas.\nPermission is required for interchange registration during the add/drop period only.\n40967-S15\n \n ","Department Code":"FRN","Course Site":"<a href= 'https://www.fivecolleges.edu/courses/SC/2015/SPRING/FRN/282/01'> Course Site </a>","Requisite":["Topics course. How do stories about moral dilemmas frame the question of what is right and what is wrong? What do these stories say about the values that are at stake? Do they provide answers and, if so, which ones? By investigating how stories revolving around moral conflicts reproduce social, cultural and political contradictions, as well as ethical ones, this course allows students to reflect on some of the major issues that have shaped the moral debate in post-revolutionary France. Readings by Balzac, Hugo, Zola, Gide, Camus, Sartre and Benameur. Prerequisite: one course above FRN 230."]},"color":"rgb(236, 69, 118)","size":10.0},{"label":"FRN-230","x":2.0,"y":1.0,"id":"12","attributes":{"Title":"COLLOQUIUM IN FRENCH STUDIES","Description":"Spring\n2016\nFrench\n230\nSmith College\nA gateway to more advanced courses. These colloquia develop skills in expository writing and critical thinking in French. Materials include novels, films, essays and cultural documents. Students may receive credit for only one section of 230. Enrollment limited to 18. Basis for the major. Prerequisite: 220 or permission of the instructor. In this course, students study fiction, memoir, slam poetry and hip-hop authored by residents of France's multi-ethnic suburbs and housing projects, also known as the \nand \nWe examine the question of whether \nauthors can escape various pressures: to become native informants; to write realistic rather than fantastical novels; to leave the \"ghetto\"; to denounce the sometimes difficult traditions, religions, neighborhoods and family members that have challenged but also molded them. Often seen as spaces of regression and decay, the \nnevertheless produce vibrant cultural expressions that beg the question: is the \na mere suburb of French cultural life, or more like one of its centers?\nTopic: \"Banlieue Lit\".\nPermission is required for interchange registration during the add/drop period only.\n37985-S16\n \n ","Department Code":"FRN","Course Site":"<a href= 'https://www.fivecolleges.edu/courses/SC/2016/SPRING/FRN/230/01'> Course Site </a>","Requisite":["A gateway to more advanced courses. These colloquia develop skills in expository writing and critical thinking in French. Materials include novels, films, essays and cultural documents. Students may receive credit for only one section of 230. Enrollment limited to 18. Basis for the major. Prerequisite: 220 or permission of the instructor. In this course, students study fiction, memoir, slam poetry and hip-hop authored by residents of France's multi-ethnic suburbs and housing projects, also known as the "]},"color":"rgb(236, 69, 118)","size":10.0},{"label":"FRN-295","x":16.5,"y":1.0,"id":"13","attributes":{"Title":"FRENCH TRANSLATION IN PRACTICE","Description":"Spring\n2016\nFrench\n295\nSmith College\nPracticum in French; must be taken concurrently with CLT 150. Students read short texts in translation theory, study translation techniques and strategies, compare versions of translated texts, and produce their own translations of French texts. Readings and discussions conducted in French. Prerequisite: 2 courses above 230 or permission of the instructor. The combination of CLT 150 and FRN 295 for a total of 4 credits can count toward the courses required to complete the FRN major.\nMust register for CLT 150 concurrently.\nPermission is required for interchange registration during the add/drop period only.\n40445-S16\n \n ","Department Code":"FRN","Course Site":"<a href= 'https://www.fivecolleges.edu/courses/SC/2016/SPRING/FRN/295/01'> Course Site </a>","Requisite":["Practicum in French; must be taken concurrently with CLT 150. Students read short texts in translation theory, study translation techniques and strategies, compare versions of translated texts, and produce their own translations of French texts. Readings and discussions conducted in French. Prerequisite: 2 courses above 230 or permission of the instructor. The combination of CLT 150 and FRN 295 for a total of 4 credits can count toward the courses required to complete the FRN major."]},"color":"rgb(236, 69, 118)","size":10.0},{"label":"FRN-392","x":17.5,"y":0.0,"id":"14","attributes":{"Title":"SEM: TOPICS IN CULTURE","Description":"Fall\n2015\nFrench\n392\nSmith College\nTopics course. In this seminar, we examine how popular French comedies have recently relied on stereotypes to promote a national conversation about social, racial, sexual and religious identities. Among the issues considered: Why are these comedies popular? What are the cultural and national boundaries of comedy? Who is laughing (or not) and why? Are all stereotypes equal? Can laughter promote social progress? Is it possible to identify larger political or cultural concerns hidden behind the use of stereotypes\u00a0in these films?\u00a0Weekly or biweekly film showings. Readings in film criticism and relevant fields.\nTopic: Stereotypes in French Cinema.  Instructor permission.   Not open to first-years, sophomores\nPermission is required for interchange registration during all registration periods.\n20438-F15\n \n ","Department Code":"FRN","Course Site":"<a href= 'https://www.fivecolleges.edu/courses/SC/2015/FALL/FRN/392/01'> Course Site </a>","Requisite":[]},"color":"rgb(236, 69, 118)","size":10.0},{"label":"FRN-120","x":4.0,"y":1.0,"id":"15","attributes":{"Title":"INTERMEDIATE FRENCH","Description":"Spring\n2016\nFrench\n120\nSmith College\nAn intermediate language course designed for students with two or three years of high school French. Its main objective is to develop cultural awareness and the ability to speak and write in French through exposure to a variety of media (literary texts, newspaper articles, ads, clips, films, videos). Students completing the course normally enter 220. Enrollment limited to 18 per section.\nPermission is required for interchange registration during the add/drop period only.\n41452-S16\n \n ","Department Code":"FRN","Course Site":"<a href= 'https://www.fivecolleges.edu/courses/SC/2016/SPRING/FRN/120/01'> Course Site </a>","Requisite":[]},"color":"rgb(236, 69, 118)","size":10.0},{"label":"FRN-102","x":5.0,"y":1.0,"id":"16","attributes":{"Title":"ACCELERATED INTERMED FRENCH","Description":"Spring\n2016\nFrench\n102\nSmith College\nEmphasis on the development of oral proficiency, with special attention to reading and writing skills, using authentic materials such as poems and short stories. Students completing the course normally enter 220. Prerequisite: 101. Enrollment limited to 18 per section. Priority is given to first-year students.\nPermission is required for interchange registration during the add/drop period only.\n36199-S16\n \n ","Department Code":"FRN","Course Site":"<a href= 'https://www.fivecolleges.edu/courses/SC/2016/SPRING/FRN/102/01'> Course Site </a>","Requisite":["Emphasis on the development of oral proficiency, with special attention to reading and writing skills, using authentic materials such as poems and short stories. Students completing the course normally enter 220. Prerequisite: 101. Enrollment limited to 18 per section. Priority is given to first-year students."]},"color":"rgb(236, 69, 118)","size":10.0},{"label":"CLT-230","x":16.5,"y":0.0,"id":"17","attributes":{"Title":"UNNATURAL WOM:MOTHERS WHO KILL","Description":"Spring\n2016\nComparative Literature\n230\nSmith College\nSome cultures give the murdering mother a central place in myth and literature while others treat the subject as taboo. How is such a woman depicted-as monster, lunatic, victim, savior? What do the motives attributed to her reveal about a society's assumptions and values? What difference does it make if the author is a woman? We focus on literary texts but also consider representations in other media, especially cinema. Authors to be studied include Euripides, Seneca, Ovid, Anouilh, Christa Wolff, Walker, Morrison and others.\nPermission is required for interchange registration during the add/drop period only.\n41376-S16\n \n ","Department Code":"CLT","Course Site":"<a href= 'https://www.fivecolleges.edu/courses/SC/2016/SPRING/CLT/230/01'> Course Site </a>","Requisite":[]},"color":"rgb(69, 144, 77)","size":10.0},{"label":"FRN-380","x":18.5,"y":0.0,"id":"18","attributes":{"Title":"TOPICS/FRENCH CULTURAL STUDIES","Description":"Spring\n2016\nFrench\n380\nSmith College\nTopics course. What is French America, or\u00a0\n? What is the nature of the French-American relationship, historically and today? At the height of the contemporary Franco-American culture wars, France and the United States seemed to be polar opposites. Yet at one time parts of the United States spoke French, lived and laughed in French, cried and died in French. Must French now be translated in America? Through what cultural mechanisms is Frenchness expressed by Americans? In what languages does one write French America today? We answer such questions in our exploration of the French experience of North America from the 17th to the 21st century.\nTopic: France in America.\nPermission is required for interchange registration during the add/drop period only.\n41456-S16\n \n ","Department Code":"FRN","Course Site":"<a href= 'https://www.fivecolleges.edu/courses/SC/2016/SPRING/FRN/380/01'> Course Site </a>","Requisite":[]},"color":"rgb(236, 69, 118)","size":10.0},{"label":"FRN-252","x":9.0,"y":1.0,"id":"19","attributes":{"Title":"FRENCH CINEMA","Description":"Fall\n2015\nFrench\n252\nSmith College\nTopics course. From Paris to Fort-de-France, Montreal to Dakar, we study how various filmmakers from the Francophone world present urban spaces as sites of conflict, solidarity, alienation and self-discovery. How do these portraits confirm or challenge the distinction between urban and nonurban? How does the image of the city shift for \"insiders\" and \"outsiders\"? Other topics to be discussed include immigration, colonialism and globalization. Works by Sembene Ousmane, Denys Arcand, Mweze Ngangura and Euzhan Palcy. Offered in French. Prerequisite: 230, or permission of the instructor. Weekly required screenings. 252 may be repeated for credit with another topic.\nTopic: Cities of Light: Urban Spaces in Francophone Film.\nPermission is required for interchange registration during the add/drop period only.\n20436-F15\n \n ","Department Code":"FRN","Course Site":"<a href= 'https://www.fivecolleges.edu/courses/SC/2015/FALL/FRN/252/01'> Course Site </a>","Requisite":["Topics course. From Paris to Fort-de-France, Montreal to Dakar, we study how various filmmakers from the Francophone world present urban spaces as sites of conflict, solidarity, alienation and self-discovery. How do these portraits confirm or challenge the distinction between urban and nonurban? How does the image of the city shift for \"insiders\" and \"outsiders\"? Other topics to be discussed include immigration, colonialism and globalization. Works by Sembene Ousmane, Denys Arcand, Mweze Ngangura and Euzhan Palcy. Offered in French. Prerequisite: 230, or permission of the instructor. Weekly required screenings. 252 may be repeated for credit with another topic."]},"color":"rgb(236, 69, 118)","size":10.0},{"label":"FRN-300","x":19.5,"y":1.0,"id":"20","attributes":{"Title":"LANGUAGE AND IDENTITY","Description":"Fall\n2015\nFrench\n300\nSmith College\nA course in advanced composition for students who wish to improve their mastery of some of the more difficult points of French grammar, syntax and usage, as they reflect on the role of language in shaping individual and national identity, from the 16th century to the present day. Readings and discussions on topics such as linguistic policy and cultural politics, the feminization of the French language, and defending against the invasion of English by legislating the use of French within France and Quebec. Prerequisite: two courses in French studies at the 250 level or above, or permission of the instructor.\nPermission is required for interchange registration during the add/drop period only.\n10720-F15\n \n ","Department Code":"FRN","Course Site":"<a href= 'https://www.fivecolleges.edu/courses/SC/2015/FALL/FRN/300/01'> Course Site </a>","Requisite":["A course in advanced composition for students who wish to improve their mastery of some of the more difficult points of French grammar, syntax and usage, as they reflect on the role of language in shaping individual and national identity, from the 16th century to the present day. Readings and discussions on topics such as linguistic policy and cultural politics, the feminization of the French language, and defending against the invasion of English by legislating the use of French within France and Quebec. Prerequisite: two courses in French studies at the 250 level or above, or permission of the instructor."]},"color":"rgb(236, 69, 118)","size":10.0},{"label":"FRN-251","x":1.0,"y":1.0,"id":"21","attributes":{"Title":"THE FRENCH MEDIA, NOW & THEN","Description":"Fall\n2015\nFrench\n251\nSmith College\nA broad overview of the different media and their histories in the French and Francophone world as well as an overview of French social, economic, political and cultural issues. Students acquire essential tools for media analysis: identifying political orientation, detecting bias, tracking controversies over time, putting quotes in context, and identifying missing voices in the narrative. Students can expect to read the leading newspapers every week and grapple with events as they happen. Prerequisite: 230 or permission of the instructor. A study of contemporary French social, economic, political and cultural issues through daily readings of \u00a0French magazines and newspapers online such as \n, \n, \n, \n.\nTopic: The French Press Online.\nPermission is required for interchange registration during the add/drop period only.\n17975-F15\n \n ","Department Code":"FRN","Course Site":"<a href= 'https://www.fivecolleges.edu/courses/SC/2015/FALL/FRN/251/01'> Course Site </a>","Requisite":["A broad overview of the different media and their histories in the French and Francophone world as well as an overview of French social, economic, political and cultural issues. Students acquire essential tools for media analysis: identifying political orientation, detecting bias, tracking controversies over time, putting quotes in context, and identifying missing voices in the narrative. Students can expect to read the leading newspapers every week and grapple with events as they happen. Prerequisite: 230 or permission of the instructor. A study of contemporary French social, economic, political and cultural issues through daily readings of \u00a0French magazines and newspapers online such as "]},"color":"rgb(236, 69, 118)","size":10.0},{"label":"FRN-580","x":20.5,"y":0.0,"id":"22","attributes":{"Title":"ADVANCED STUDIES","Description":"Spring\n2016\nFrench\n580\nSmith College\nArranged in consultation with the department.\nPermission Instructor/Chair.  , Limited to graduate students\nPermission is required for interchange registration during all registration periods.\n30452-S16\n \n ","Department Code":"FRN","Course Site":"<a href= 'https://www.fivecolleges.edu/courses/SC/2016/SPRING/FRN/580/0'> Course Site </a>","Requisite":[]},"color":"rgb(236, 69, 118)","size":10.0},{"label":"FRN-404","x":21.5,"y":0.0,"id":"23","attributes":{"Title":"SPECIAL STUDIES","Description":"Spring\n2016\nFrench\n404\nSmith College\nAdmission by permission of the department; normally for junior and senior majors and for qualified juniors and seniors from other departments.\nPermission Instructor/Chair.   Limited to FRN majors Not open to first-years\nPermission is required for interchange registration during all registration periods.\n30448-S16\n \n ","Department Code":"FRN","Course Site":"<a href= 'https://www.fivecolleges.edu/courses/SC/2016/SPRING/FRN/404/0'> Course Site </a>","Requisite":[]},"color":"rgb(236, 69, 118)","size":10.0},{"label":"FRN-101","x":10.0,"y":1.0,"id":"24","attributes":{"Title":"ACCELERATED ELEMENTARY FRENCH","Description":"Fall\n2015\nFrench\n101\nSmith College\nAn accelerated introduction to French for real beginners based on the video method \n Development of the ability to communicate confidently with an emphasis on the acquisition of listening, speaking and writing skills, as well as cultural awareness. Four class meetings per week plus required daily video and audio work. Students completing the course normally enter 102 or 103. Students must complete both 101 and 102 or 103 to fulfill the Latin honors distribution requirement for a foreign language. Enrollment limited to 18 per section. No spring preregistration allowed.\nPermission is required for interchange registration during the add/drop period only.\n15887-F15\n \n ","Department Code":"FRN","Course Site":"<a href= 'https://www.fivecolleges.edu/courses/SC/2015/FALL/FRN/101/01'> Course Site </a>","Requisite":[]},"color":"rgb(236, 69, 118)","size":10.0},{"label":"FRN-264","x":3.0,"y":2.0,"id":"25","attributes":{"Title":"ENCOUNTRNG OTHERS/ANCIEN REGIM","Description":"Spring\n2016\nFrench\n264\nSmith College\nHow was France's cultural and political identity shaped by its encounters with the Other as it expanded trade and its conquest of foreign political and cultural powers such as the Ottoman empire and the newly discovered nations of the Americas, Africa and Tahiti? How did the concept of the foreigner evolve as confrontations with other nations, other religions, other ethnicities put into question France's conception of its own society and culture? We examine a range of texts (treatises, pamphlets, novels, theatre,\u00a0\n) in which \"otherness\" and foreignness is explored. Readings from Montaigne, Moliere, Montesquieu, Graffigny, Voltaire, Diderot, Gouges, Duras and Condorcet. Prerequisite: FRN 230 or permission of the instructor.\nPermission is required for interchange registration during the add/drop period only.\n41453-S16\n \n ","Department Code":"FRN","Course Site":"<a href= 'https://www.fivecolleges.edu/courses/SC/2016/SPRING/FRN/264/01'> Course Site </a>","Requisite":[") in which \"otherness\" and foreignness is explored. Readings from Montaigne, Moliere, Montesquieu, Graffigny, Voltaire, Diderot, Gouges, Duras and Condorcet. Prerequisite: FRN 230 or permission of the instructor."]},"color":"rgb(236, 69, 118)","size":10.0},{"label":"FRN-262","x":0.0,"y":1.0,"id":"26","attributes":{"Title":"AFTER ALGERIA: REV,RPBLC, RACE","Description":"Spring\n2016\nFrench\n262\nSmith College\nFor the last two centuries, one could argue that it is the Franco-Algerian relationship that has been decisive in the construction of modern France. From the colonial conquest in the early 19th century through independence in 1962, Algeria has evoked passions on both sides of the Mediterranean Sea, passions frequently resulting in violence that has not entirely subsided. Memory of a conflictual present and past has required continual mediation among involved actors. In the 50-plus years that have passed since Algerian independence, France and the French have increasingly confronted echoes of their colonial past as a result of pervasive debates around immigration, multiculturalism and national identity. Through a variety of perspectives and readings, we explore a post-Algerian French society that appears to be permanently marked by its Algerian experience. Can a late-20th-century discourse of socioeconomic, cultural, ethnic and religious diversity, all shaped by the Algerian episode, be reconciled with Republican norms? To what extent has the experience in and of Algeria transformed contemporary French culture? In what ways can one speak of the Algerian experience in revolutionary terms? Prerequisite: 230 or permission of the instructor.\nPermission is required for interchange registration during the add/drop period only.\n40444-S16\n \n ","Department Code":"FRN","Course Site":"<a href= 'https://www.fivecolleges.edu/courses/SC/2016/SPRING/FRN/262/01'> Course Site </a>","Requisite":["For the last two centuries, one could argue that it is the Franco-Algerian relationship that has been decisive in the construction of modern France. From the colonial conquest in the early 19th century through independence in 1962, Algeria has evoked passions on both sides of the Mediterranean Sea, passions frequently resulting in violence that has not entirely subsided. Memory of a conflictual present and past has required continual mediation among involved actors. In the 50-plus years that have passed since Algerian independence, France and the French have increasingly confronted echoes of their colonial past as a result of pervasive debates around immigration, multiculturalism and national identity. Through a variety of perspectives and readings, we explore a post-Algerian French society that appears to be permanently marked by its Algerian experience. Can a late-20th-century discourse of socioeconomic, cultural, ethnic and religious diversity, all shaped by the Algerian episode, be reconciled with Republican norms? To what extent has the experience in and of Algeria transformed contemporary French culture? In what ways can one speak of the Algerian experience in revolutionary terms? Prerequisite: 230 or permission of the instructor."]},"color":"rgb(236, 69, 118)","size":10.0},{"label":"CLT-150","x":16.5,"y":2.0,"id":"27","attributes":{"Title":"ART OF TRANSLAT:POET,POL,PRACT","Description":"Spring\n2016\nComparative Literature\n150\nSmith College\nWe hear and read translations all the time: on television news, in radio interviews, in movie subtitles, in international bestsellers. But translations don't shift texts transparently from one language to another. Rather, they revise, censor and rewrite original works, to challenge the past and to speak to new readers. We explore translation in a range of contexts by hearing lectures by experts in the history, theory and practice of translation. Knowledge of a foreign language useful but not required. Graded S/U only. Can be taken concurrently with FRN 295 for 4 credits.\nPermission is required for interchange registration during the add/drop period only.\n38913-S16\n \n ","Department Code":"CLT","Course Site":"<a href= 'https://www.fivecolleges.edu/courses/SC/2016/SPRING/CLT/150/01'> Course Site </a>","Requisite":[]},"color":"rgb(69, 144, 77)","size":10.0},{"label":"FRN-220","x":5.0,"y":2.0,"id":"28","attributes":{"Title":"HIGH INTERMEDIATE FRENCH","Description":"Spring\n2016\nFrench\n220\nSmith College\nReview of communicative skills through writing and class discussion. Materials include a movie, a comic book, a play and a novel. Prerequisite: three or four years of high school French; 102, 103 or 120; or permission of the instructor. Students completing the course normally enter 230. Enrollment limited to 18 per section.\nPermission is required for interchange registration during the add/drop period only.\n30433-S16\n \n ","Department Code":"FRN","Course Site":"<a href= 'https://www.fivecolleges.edu/courses/SC/2016/SPRING/FRN/220/01'> Course Site </a>","Requisite":["Review of communicative skills through writing and class discussion. Materials include a movie, a comic book, a play and a novel. Prerequisite: three or four years of high school French; 102, 103 or 120; or permission of the instructor. Students completing the course normally enter 230. Enrollment limited to 18 per section."]},"color":"rgb(236, 69, 118)","size":10.0},{"label":"FRN-272","x":7.0,"y":1.0,"id":"29","attributes":{"Title":"FRENCH INTELLECTUALS/ACTIVISTS","Description":"Fall\n2015\nFrench\n272\nSmith College\nWhy can some writers be called intellectuals? What is an intellectual? Why are French intellectuals unique? This course studies the emergence of political activism and the figure of the French \"intellectual engage\" through readings from key social and historical moments and from a variety of genres. We trace how public debates on highly controversial topics such as intolerance, fanaticism, the death penalty, feminism, racism, and the role of media have influenced intellectuals to become committed to transforming French politics and society. Texts include writings by Montaigne, Moliere, Voltaire, Hugo, Zola, Sartre, Beauvoir, Halimi, Bourdieu and others. Prerequisite: 230 or permission of the instructor.\nPermission is required for interchange registration during the add/drop period only.\n20866-F15\n \n ","Department Code":"FRN","Course Site":"<a href= 'https://www.fivecolleges.edu/courses/SC/2015/FALL/FRN/272/01'> Course Site </a>","Requisite":["Why can some writers be called intellectuals? What is an intellectual? Why are French intellectuals unique? This course studies the emergence of political activism and the figure of the French \"intellectual engage\" through readings from key social and historical moments and from a variety of genres. We trace how public debates on highly controversial topics such as intolerance, fanaticism, the death penalty, feminism, racism, and the role of media have influenced intellectuals to become committed to transforming French politics and society. Texts include writings by Montaigne, Moliere, Voltaire, Hugo, Zola, Sartre, Beauvoir, Halimi, Bourdieu and others. Prerequisite: 230 or permission of the instructor."]},"color":"rgb(236, 69, 118)","size":10.0},{"label":"THE-101","x":7.0,"y":0.0,"id":"30","attributes":{"Title":"THE-101","Description":"not offered in the last 4 semesters","Department Code":"THE","Course Site":"","Requisite":""},"color":"rgb(126, 83, 86)","size":10.0},{"label":"THE-300","x":0.0,"y":0.0,"id":"31","attributes":{"Title":"THE-300","Description":"not offered in the last 4 semesters","Department Code":"THE","Course Site":"","Requisite":""},"color":"rgb(126, 83, 86)","size":10.0},{"label":"THE-102","x":8.5,"y":0.0,"id":"32","attributes":{"Title":"THE-102","Description":"not offered in the last 4 semesters","Department Code":"THE","Course Site":"","Requisite":""},"color":"rgb(126, 83, 86)","size":10.0},{"label":"THE-103","x":10.5,"y":0.0,"id":"33","attributes":{"Title":"THE-103","Description":"not offered in the last 4 semesters","Department Code":"THE","Course Site":"","Requisite":""},"color":"rgb(126, 83, 86)","size":10.0},{"label":"THE-230","x":6.0,"y":0.0,"id":"34","attributes":{"Title":"THE-230","Description":"not offered in the last 4 semesters","Department Code":"THE","Course Site":"","Requisite":""},"color":"rgb(126, 83, 86)","size":10.0},{"label":"THE-220","x":3.0,"y":0.0,"id":"35","attributes":{"Title":"THE-220","Description":"not offered in the last 4 semesters","Department Code":"THE","Course Site":"","Requisite":""},"color":"rgb(126, 83, 86)","size":10.0},{"label":"THE-250","x":19.5,"y":0.0,"id":"36","attributes":{"Title":"THE-250","Description":"not offered in the last 4 semesters","Department Code":"THE","Course Site":"","Requisite":""},"color":"rgb(126, 83, 86)","size":10.0}]}